{"_id":"offline-plugin","_rev":"61-323df9290a3dcdae7bd188c04fe0693e","name":"offline-plugin","description":"offline-plugin for webpack","dist-tags":{"latest":"4.5.5","next":"4.5.1","unstable":"4.5.0"},"versions":{"0.0.1":{"name":"offline-plugin","version":"0.0.1","description":"Webpack offline-plugin (WIP)","main":"index.js","scripts":{"test":"echo \"Error: no test specified\" && exit 1"},"repository":{"type":"git","url":"https://github.com/NekR/offline-plugin.git"},"author":{"name":"Arthur Stolyar","email":"nekr.fabula@gmail.com"},"license":"MIT","bugs":{"url":"https://github.com/NekR/offline-plugin/issues"},"homepage":"https://github.com/NekR/offline-plugin","gitHead":"f64464d92f06994f972f069632a040b75f13d00f","_id":"offline-plugin@0.0.1","_shasum":"486467998313d5d26a8419dab1524f650d1c8953","_from":".","_npmVersion":"2.7.4","_nodeVersion":"0.12.2","_npmUser":{"name":"nekr","email":"nekr.fabula@gmail.com"},"dist":{"shasum":"486467998313d5d26a8419dab1524f650d1c8953","tarball":"https://registry.npmjs.org/offline-plugin/-/offline-plugin-0.0.1.tgz"},"maintainers":[{"name":"nekr","email":"nekr.fabula@gmail.com"}],"directories":{}},"0.0.2":{"name":"offline-plugin","version":"0.0.2","description":"offline-plugin for webpack","main":"lib/index.js","files":["lib/","misc/","runtime.js"],"scripts":{"test":"echo \"Error: no test specified\" && exit 1"},"repository":{"type":"git","url":"https://github.com/NekR/offline-plugin.git"},"author":{"name":"Arthur Stolyar","email":"nekr.fabula@gmail.com"},"license":"MIT","dependencies":{"deep-extend":"^0.4.0","ejs":"^2.3.4","serviceworker-cache-polyfill":"^3.0.0","loader-utils":"0.2.x"},"bugs":{"url":"https://github.com/NekR/offline-plugin/issues"},"homepage":"https://github.com/NekR/offline-plugin","gitHead":"c2ba0fc02c2a776c6750230eb1c1f575bfaea977","_id":"offline-plugin@0.0.2","_shasum":"94ea887f8bde3fa4285ce97d1ea601bbc1948875","_from":".","_npmVersion":"2.7.4","_nodeVersion":"0.12.2","_npmUser":{"name":"nekr","email":"nekr.fabula@gmail.com"},"dist":{"shasum":"94ea887f8bde3fa4285ce97d1ea601bbc1948875","tarball":"https://registry.npmjs.org/offline-plugin/-/offline-plugin-0.0.2.tgz"},"maintainers":[{"name":"nekr","email":"nekr.fabula@gmail.com"}],"directories":{}},"1.0.0":{"name":"offline-plugin","version":"1.0.0","description":"offline-plugin for webpack","main":"lib/index.js","files":["lib/","runtime.js","empty-entry.js"],"scripts":{"test":"echo \"Error: no test specified\" && exit 1"},"repository":{"type":"git","url":"https://github.com/NekR/offline-plugin.git"},"author":{"name":"Arthur Stolyar","email":"nekr.fabula@gmail.com"},"license":"MIT","dependencies":{"deep-extend":"^0.4.0","ejs":"^2.3.4","loader-utils":"0.2.x","minimatch":"^2.0.10","serviceworker-cache-polyfill":"^3.0.0"},"bugs":{"url":"https://github.com/NekR/offline-plugin/issues"},"homepage":"https://github.com/NekR/offline-plugin","keywords":["webpack","plugin","offline","cache","service-worker","serviceworker","appcache","application cache"],"gitHead":"15cbe235c8652ba11c8d45f4856187d6e322f5ea","_id":"offline-plugin@1.0.0","_shasum":"7fbddfa545ff22aebbbc06e10a81c3740c2ef801","_from":".","_npmVersion":"2.7.4","_nodeVersion":"0.12.2","_npmUser":{"name":"nekr","email":"nekr.fabula@gmail.com"},"dist":{"shasum":"7fbddfa545ff22aebbbc06e10a81c3740c2ef801","tarball":"https://registry.npmjs.org/offline-plugin/-/offline-plugin-1.0.0.tgz"},"maintainers":[{"name":"nekr","email":"nekr.fabula@gmail.com"}],"directories":{}},"1.0.1":{"name":"offline-plugin","version":"1.0.1","description":"offline-plugin for webpack","main":"lib/index.js","files":["lib/","runtime.js","empty-entry.js"],"scripts":{"test":"echo \"Error: no test specified\" && exit 1"},"repository":{"type":"git","url":"https://github.com/NekR/offline-plugin.git"},"author":{"name":"Arthur Stolyar","email":"nekr.fabula@gmail.com"},"license":"MIT","dependencies":{"deep-extend":"^0.4.0","ejs":"^2.3.4","loader-utils":"0.2.x","minimatch":"^2.0.10","serviceworker-cache-polyfill":"^3.0.0"},"bugs":{"url":"https://github.com/NekR/offline-plugin/issues"},"homepage":"https://github.com/NekR/offline-plugin","keywords":["webpack","plugin","offline","cache","service-worker","serviceworker","appcache","application cache"],"gitHead":"6f432704261b81111f834d9c253a54d75daa5c3b","_id":"offline-plugin@1.0.1","_shasum":"f84e5dec5dcbc43196bb17dd11f970ef63bd953e","_from":".","_npmVersion":"2.7.4","_nodeVersion":"0.12.2","_npmUser":{"name":"nekr","email":"nekr.fabula@gmail.com"},"dist":{"shasum":"f84e5dec5dcbc43196bb17dd11f970ef63bd953e","tarball":"https://registry.npmjs.org/offline-plugin/-/offline-plugin-1.0.1.tgz"},"maintainers":[{"name":"nekr","email":"nekr.fabula@gmail.com"}],"directories":{}},"1.0.2":{"name":"offline-plugin","version":"1.0.2","description":"offline-plugin for webpack","main":"lib/index.js","files":["lib/","runtime.js","empty-entry.js"],"scripts":{"test":"echo \"Error: no test specified\" && exit 1"},"repository":{"type":"git","url":"https://github.com/NekR/offline-plugin.git"},"author":{"name":"Arthur Stolyar","email":"nekr.fabula@gmail.com"},"license":"MIT","dependencies":{"deep-extend":"^0.4.0","ejs":"^2.3.4","loader-utils":"0.2.x","minimatch":"^2.0.10","serviceworker-cache-polyfill":"^3.0.0"},"bugs":{"url":"https://github.com/NekR/offline-plugin/issues"},"homepage":"https://github.com/NekR/offline-plugin","keywords":["webpack","plugin","offline","cache","service-worker","serviceworker","appcache","application cache"],"gitHead":"614d0caf9ce4de3bf7b48e30f0c530de0676825f","_id":"offline-plugin@1.0.2","_shasum":"4107a68c5050b18bc628f4e5a9e63b7fc394b7c1","_from":".","_npmVersion":"2.7.4","_nodeVersion":"0.12.2","_npmUser":{"name":"nekr","email":"nekr.fabula@gmail.com"},"dist":{"shasum":"4107a68c5050b18bc628f4e5a9e63b7fc394b7c1","tarball":"https://registry.npmjs.org/offline-plugin/-/offline-plugin-1.0.2.tgz"},"maintainers":[{"name":"nekr","email":"nekr.fabula@gmail.com"}],"directories":{}},"1.0.3":{"name":"offline-plugin","version":"1.0.3","description":"offline-plugin for webpack","main":"lib/index.js","files":["lib/","runtime.js","empty-entry.js"],"scripts":{"test":"echo \"Error: no test specified\" && exit 1"},"repository":{"type":"git","url":"https://github.com/NekR/offline-plugin.git"},"author":{"name":"Arthur Stolyar","email":"nekr.fabula@gmail.com"},"license":"MIT","dependencies":{"deep-extend":"^0.4.0","ejs":"^2.3.4","loader-utils":"0.2.x","minimatch":"^2.0.10","serviceworker-cache-polyfill":"^3.0.0"},"bugs":{"url":"https://github.com/NekR/offline-plugin/issues"},"homepage":"https://github.com/NekR/offline-plugin","keywords":["webpack","plugin","offline","cache","service-worker","serviceworker","appcache","application cache"],"gitHead":"288bb69f3483d258537a643b3286f6db599f6dc9","_id":"offline-plugin@1.0.3","_shasum":"ca5d447bd45a0d7fd05f006d511df2688adf0df6","_from":".","_npmVersion":"2.7.4","_nodeVersion":"0.12.2","_npmUser":{"name":"nekr","email":"nekr.fabula@gmail.com"},"dist":{"shasum":"ca5d447bd45a0d7fd05f006d511df2688adf0df6","tarball":"https://registry.npmjs.org/offline-plugin/-/offline-plugin-1.0.3.tgz"},"maintainers":[{"name":"nekr","email":"nekr.fabula@gmail.com"}],"directories":{}},"1.1.0":{"name":"offline-plugin","version":"1.1.0","description":"offline-plugin for webpack","main":"lib/index.js","files":["lib/","runtime.js","empty-entry.js"],"scripts":{"test":"echo \"Error: no test specified\" && exit 1"},"repository":{"type":"git","url":"https://github.com/NekR/offline-plugin.git"},"author":{"name":"Arthur Stolyar","email":"nekr.fabula@gmail.com"},"license":"MIT","dependencies":{"deep-extend":"^0.4.0","ejs":"^2.3.4","loader-utils":"0.2.x","minimatch":"^2.0.10","serviceworker-cache-polyfill":"^3.0.0"},"bugs":{"url":"https://github.com/NekR/offline-plugin/issues"},"homepage":"https://github.com/NekR/offline-plugin","keywords":["webpack","plugin","offline","cache","service-worker","serviceworker","appcache","application cache"],"gitHead":"f8ad8741f090736f098e3c146c83b508870a0286","_id":"offline-plugin@1.1.0","_shasum":"f4f97df9a7d88fbbc52198154cc421d981ef5c4b","_from":".","_npmVersion":"2.7.4","_nodeVersion":"0.12.2","_npmUser":{"name":"nekr","email":"nekr.fabula@gmail.com"},"dist":{"shasum":"f4f97df9a7d88fbbc52198154cc421d981ef5c4b","tarball":"https://registry.npmjs.org/offline-plugin/-/offline-plugin-1.1.0.tgz"},"maintainers":[{"name":"nekr","email":"nekr.fabula@gmail.com"}],"directories":{}},"1.2.0":{"name":"offline-plugin","version":"1.2.0","description":"offline-plugin for webpack","main":"lib/index.js","files":["lib/","runtime.js","empty-entry.js"],"scripts":{"test":"echo \"Error: no test specified\" && exit 1"},"repository":{"type":"git","url":"https://github.com/NekR/offline-plugin.git"},"author":{"name":"Arthur Stolyar","email":"nekr.fabula@gmail.com"},"license":"MIT","dependencies":{"deep-extend":"^0.4.0","ejs":"^2.3.4","loader-utils":"0.2.x","minimatch":"^2.0.10","serviceworker-cache-polyfill":"^3.0.0"},"bugs":{"url":"https://github.com/NekR/offline-plugin/issues"},"homepage":"https://github.com/NekR/offline-plugin","keywords":["webpack","plugin","offline","cache","service-worker","serviceworker","appcache","application cache"],"gitHead":"4840bf3e5e1fdd7c8a78ce2ac083e411a38701be","_id":"offline-plugin@1.2.0","_shasum":"e0ae2db5c673e0f6e0e54dbfe6d9ce7823db13e8","_from":".","_npmVersion":"2.7.4","_nodeVersion":"0.12.2","_npmUser":{"name":"nekr","email":"nekr.fabula@gmail.com"},"dist":{"shasum":"e0ae2db5c673e0f6e0e54dbfe6d9ce7823db13e8","tarball":"https://registry.npmjs.org/offline-plugin/-/offline-plugin-1.2.0.tgz"},"maintainers":[{"name":"nekr","email":"nekr.fabula@gmail.com"}],"directories":{}},"1.2.1":{"name":"offline-plugin","version":"1.2.1","description":"offline-plugin for webpack","main":"lib/index.js","files":["lib/","runtime.js","empty-entry.js"],"scripts":{"test":"echo \"Error: no test specified\" && exit 1"},"repository":{"type":"git","url":"https://github.com/NekR/offline-plugin.git"},"author":{"name":"Arthur Stolyar","email":"nekr.fabula@gmail.com"},"license":"MIT","dependencies":{"deep-extend":"^0.4.0","ejs":"^2.3.4","loader-utils":"0.2.x","minimatch":"^2.0.10","serviceworker-cache-polyfill":"^3.0.0"},"bugs":{"url":"https://github.com/NekR/offline-plugin/issues"},"homepage":"https://github.com/NekR/offline-plugin","keywords":["webpack","plugin","offline","cache","service-worker","serviceworker","appcache","application cache"],"gitHead":"66bacdeb6cd2d1652448f7e32d32f2184a1d5c7c","_id":"offline-plugin@1.2.1","_shasum":"a815bf74374bea8ddb42ef9c598a7de90701c623","_from":".","_npmVersion":"2.7.4","_nodeVersion":"0.12.2","_npmUser":{"name":"nekr","email":"nekr.fabula@gmail.com"},"dist":{"shasum":"a815bf74374bea8ddb42ef9c598a7de90701c623","tarball":"https://registry.npmjs.org/offline-plugin/-/offline-plugin-1.2.1.tgz"},"maintainers":[{"name":"nekr","email":"nekr.fabula@gmail.com"}],"directories":{}},"1.3.0":{"name":"offline-plugin","version":"1.3.0","description":"offline-plugin for webpack","main":"lib/index.js","files":["lib/","runtime.js","empty-entry.js"],"scripts":{"test":"echo \"Error: no test specified\" && exit 1","build":"babel src/ -d lib/","watch":"npm run build -- --watch"},"repository":{"type":"git","url":"https://github.com/NekR/offline-plugin.git"},"author":{"name":"Arthur Stolyar","email":"nekr.fabula@gmail.com"},"license":"MIT","dependencies":{"deep-extend":"^0.4.0","ejs":"^2.3.4","loader-utils":"0.2.x","minimatch":"^2.0.10","serviceworker-cache-polyfill":"^3.0.0"},"bugs":{"url":"https://github.com/NekR/offline-plugin/issues"},"homepage":"https://github.com/NekR/offline-plugin","keywords":["webpack","plugin","offline","cache","service-worker","serviceworker","appcache","application cache"],"devDependencies":{"babel":"^5.8.23"},"gitHead":"b67a654d23f73f82e33d18b8698db903a825e67f","_id":"offline-plugin@1.3.0","_shasum":"76f49533c676079fa57f6b1be784086007a420f9","_from":".","_npmVersion":"2.7.4","_nodeVersion":"0.12.2","_npmUser":{"name":"nekr","email":"nekr.fabula@gmail.com"},"dist":{"shasum":"76f49533c676079fa57f6b1be784086007a420f9","tarball":"https://registry.npmjs.org/offline-plugin/-/offline-plugin-1.3.0.tgz"},"maintainers":[{"name":"nekr","email":"nekr.fabula@gmail.com"}],"directories":{}},"1.3.1":{"name":"offline-plugin","version":"1.3.1","description":"offline-plugin for webpack","main":"lib/index.js","files":["lib/","runtime.js","empty-entry.js"],"scripts":{"test":"echo \"Error: no test specified\" && exit 1","build":"babel src/ -d lib/","watch":"npm run build -- --watch"},"repository":{"type":"git","url":"https://github.com/NekR/offline-plugin.git"},"author":{"name":"Arthur Stolyar","email":"nekr.fabula@gmail.com"},"license":"MIT","dependencies":{"deep-extend":"^0.4.0","ejs":"^2.3.4","loader-utils":"0.2.x","minimatch":"^2.0.10","serviceworker-cache-polyfill":"^3.0.0"},"bugs":{"url":"https://github.com/NekR/offline-plugin/issues"},"homepage":"https://github.com/NekR/offline-plugin","keywords":["webpack","plugin","offline","cache","service-worker","serviceworker","appcache","application cache"],"devDependencies":{"babel":"^5.8.23"},"gitHead":"1402f19661218f9a79fcdd43c7ac89dfa2d6086d","_id":"offline-plugin@1.3.1","_shasum":"bc6a7e6177cdef9460c9c9d7c9393bfe04579911","_from":".","_npmVersion":"2.7.4","_nodeVersion":"0.12.2","_npmUser":{"name":"nekr","email":"nekr.fabula@gmail.com"},"dist":{"shasum":"bc6a7e6177cdef9460c9c9d7c9393bfe04579911","tarball":"https://registry.npmjs.org/offline-plugin/-/offline-plugin-1.3.1.tgz"},"maintainers":[{"name":"nekr","email":"nekr.fabula@gmail.com"}],"directories":{}},"2.0.0":{"name":"offline-plugin","version":"2.0.0","description":"offline-plugin for webpack","main":"lib/index.js","files":["lib/","tpls/","runtime.js","empty-entry.js"],"scripts":{"test":"echo \"Error: no test specified\" && exit 1","build":"babel src/ -d lib/","watch":"npm run build -- --watch"},"repository":{"type":"git","url":"git+https://github.com/NekR/offline-plugin.git"},"author":{"name":"Arthur Stolyar","email":"nekr.fabula@gmail.com"},"license":"MIT","dependencies":{"deep-extend":"^0.4.0","ejs":"^2.3.4","loader-utils":"0.2.x","minimatch":"^2.0.10","serviceworker-cache-polyfill":"^3.0.0"},"bugs":{"url":"https://github.com/NekR/offline-plugin/issues"},"homepage":"https://github.com/NekR/offline-plugin","keywords":["webpack","plugin","offline","cache","service-worker","serviceworker","appcache","application cache"],"devDependencies":{"babel":"^5.8.23"},"gitHead":"d71ab69cb886892f2b78601b98ca3e886f672793","_id":"offline-plugin@2.0.0","_shasum":"d03a592dd21b69a9ecf25b67aec749975af263fc","_from":".","_npmVersion":"2.14.7","_nodeVersion":"4.2.2","_npmUser":{"name":"nekr","email":"nekr.fabula@gmail.com"},"dist":{"shasum":"d03a592dd21b69a9ecf25b67aec749975af263fc","tarball":"https://registry.npmjs.org/offline-plugin/-/offline-plugin-2.0.0.tgz"},"maintainers":[{"name":"nekr","email":"nekr.fabula@gmail.com"}],"directories":{}},"2.0.1":{"name":"offline-plugin","version":"2.0.1","description":"offline-plugin for webpack","main":"lib/index.js","files":["lib/","tpls/","runtime.js","empty-entry.js"],"scripts":{"test":"echo \"Error: no test specified\" && exit 1","build":"babel src/ -d lib/","watch":"npm run build -- --watch"},"repository":{"type":"git","url":"git+https://github.com/NekR/offline-plugin.git"},"author":{"name":"Arthur Stolyar","email":"nekr.fabula@gmail.com"},"license":"MIT","dependencies":{"deep-extend":"^0.4.0","ejs":"^2.3.4","loader-utils":"0.2.x","minimatch":"^2.0.10","serviceworker-cache-polyfill":"^3.0.0"},"bugs":{"url":"https://github.com/NekR/offline-plugin/issues"},"homepage":"https://github.com/NekR/offline-plugin","keywords":["webpack","plugin","offline","cache","service-worker","serviceworker","appcache","application cache"],"devDependencies":{"babel":"^5.8.23","es6-promise":"^3.0.2"},"gitHead":"0ba30ed3f3c50d0d7b09ac04d0b63f858a3daff3","_id":"offline-plugin@2.0.1","_shasum":"7f96819ae7b155c233f8da091455b322ad736306","_from":".","_npmVersion":"2.14.7","_nodeVersion":"4.2.2","_npmUser":{"name":"nekr","email":"nekr.fabula@gmail.com"},"dist":{"shasum":"7f96819ae7b155c233f8da091455b322ad736306","tarball":"https://registry.npmjs.org/offline-plugin/-/offline-plugin-2.0.1.tgz"},"maintainers":[{"name":"nekr","email":"nekr.fabula@gmail.com"}],"directories":{}},"2.0.2":{"name":"offline-plugin","version":"2.0.2","description":"offline-plugin for webpack","main":"lib/index.js","files":["lib/","tpls/","runtime.js","empty-entry.js"],"scripts":{"test":"echo \"Error: no test specified\" && exit 1","build":"babel src/ -d lib/","watch":"npm run build -- --watch"},"repository":{"type":"git","url":"git+https://github.com/NekR/offline-plugin.git"},"author":{"name":"Arthur Stolyar","email":"nekr.fabula@gmail.com"},"license":"MIT","dependencies":{"deep-extend":"^0.4.0","ejs":"^2.3.4","es6-promise":"^3.0.2","loader-utils":"0.2.x","minimatch":"^2.0.10","serviceworker-cache-polyfill":"^3.0.0"},"bugs":{"url":"https://github.com/NekR/offline-plugin/issues"},"homepage":"https://github.com/NekR/offline-plugin","keywords":["webpack","plugin","offline","cache","service-worker","serviceworker","appcache","application cache"],"devDependencies":{"babel":"^5.8.23"},"gitHead":"862e4e0720b431e6e0cc8a1e37df4dd3c758338d","_id":"offline-plugin@2.0.2","_shasum":"db4033e2da2eb5a6fef5dcf22b9902cf918dc6e5","_from":".","_npmVersion":"2.14.7","_nodeVersion":"4.2.2","_npmUser":{"name":"nekr","email":"nekr.fabula@gmail.com"},"dist":{"shasum":"db4033e2da2eb5a6fef5dcf22b9902cf918dc6e5","tarball":"https://registry.npmjs.org/offline-plugin/-/offline-plugin-2.0.2.tgz"},"maintainers":[{"name":"nekr","email":"nekr.fabula@gmail.com"}],"directories":{}},"2.0.3":{"name":"offline-plugin","version":"2.0.3","description":"offline-plugin for webpack","main":"lib/index.js","files":["lib/","tpls/","runtime.js","empty-entry.js"],"scripts":{"test":"echo \"Error: no test specified\" && exit 1","build":"babel src/ -d lib/","watch":"npm run build -- --watch"},"repository":{"type":"git","url":"git+https://github.com/NekR/offline-plugin.git"},"author":{"name":"Arthur Stolyar","email":"nekr.fabula@gmail.com"},"license":"MIT","dependencies":{"deep-extend":"^0.4.0","ejs":"^2.3.4","es6-promise":"^3.0.2","loader-utils":"0.2.x","minimatch":"^2.0.10","serviceworker-cache-polyfill":"^3.0.0"},"bugs":{"url":"https://github.com/NekR/offline-plugin/issues"},"homepage":"https://github.com/NekR/offline-plugin","keywords":["webpack","plugin","offline","cache","service-worker","serviceworker","appcache","application cache"],"devDependencies":{"babel":"^5.8.23"},"gitHead":"0307840c906b6c72984f1a289c8fb287917f9d66","_id":"offline-plugin@2.0.3","_shasum":"cf7258b09b3cd41caa0c57aa20c63b16a4dd0dfc","_from":".","_npmVersion":"2.14.7","_nodeVersion":"4.2.2","_npmUser":{"name":"nekr","email":"nekr.fabula@gmail.com"},"dist":{"shasum":"cf7258b09b3cd41caa0c57aa20c63b16a4dd0dfc","tarball":"https://registry.npmjs.org/offline-plugin/-/offline-plugin-2.0.3.tgz"},"maintainers":[{"name":"nekr","email":"nekr.fabula@gmail.com"}],"_npmOperationalInternal":{"host":"packages-6-west.internal.npmjs.com","tmp":"tmp/offline-plugin-2.0.3.tgz_1454491783819_0.040598015300929546"},"directories":{}},"2.0.4":{"name":"offline-plugin","version":"2.0.4","description":"offline-plugin for webpack","main":"lib/index.js","files":["lib/","tpls/","runtime.js","empty-entry.js"],"scripts":{"test":"echo \"Error: no test specified\" && exit 1","build":"babel src/ -d lib/","watch":"npm run build -- --watch"},"repository":{"type":"git","url":"git+https://github.com/NekR/offline-plugin.git"},"author":{"name":"Arthur Stolyar","email":"nekr.fabula@gmail.com"},"license":"MIT","dependencies":{"deep-extend":"^0.4.0","ejs":"^2.3.4","es6-promise":"^3.0.2","loader-utils":"0.2.x","minimatch":"^2.0.10","serviceworker-cache-polyfill":"^3.0.0"},"bugs":{"url":"https://github.com/NekR/offline-plugin/issues"},"homepage":"https://github.com/NekR/offline-plugin","keywords":["webpack","plugin","offline","cache","service-worker","serviceworker","appcache","application cache"],"devDependencies":{"babel":"^5.8.23"},"gitHead":"c3c1389db23ebe8b15e91516d84ddf4daf369939","_id":"offline-plugin@2.0.4","_shasum":"b0a0bb589229b1c59cc648cd3dd55a6444f162d9","_from":".","_npmVersion":"2.14.7","_nodeVersion":"4.2.2","_npmUser":{"name":"nekr","email":"nekr.fabula@gmail.com"},"dist":{"shasum":"b0a0bb589229b1c59cc648cd3dd55a6444f162d9","tarball":"https://registry.npmjs.org/offline-plugin/-/offline-plugin-2.0.4.tgz"},"maintainers":[{"name":"nekr","email":"nekr.fabula@gmail.com"}],"_npmOperationalInternal":{"host":"packages-9-west.internal.npmjs.com","tmp":"tmp/offline-plugin-2.0.4.tgz_1454978815690_0.26963197090663016"},"directories":{}},"2.1.0":{"name":"offline-plugin","version":"2.1.0","description":"offline-plugin for webpack","main":"lib/index.js","files":["lib/","tpls/","runtime.js","empty-entry.js"],"scripts":{"test":"echo \"Error: no test specified\" && exit 1","build":"babel src/ -d lib/","watch":"npm run build -- --watch"},"repository":{"type":"git","url":"git+https://github.com/NekR/offline-plugin.git"},"author":{"name":"Arthur Stolyar","email":"nekr.fabula@gmail.com"},"license":"MIT","dependencies":{"deep-extend":"^0.4.0","ejs":"^2.3.4","es6-promise":"^3.0.2","loader-utils":"0.2.x","minimatch":"^2.0.10","serviceworker-cache-polyfill":"^3.0.0"},"bugs":{"url":"https://github.com/NekR/offline-plugin/issues"},"homepage":"https://github.com/NekR/offline-plugin","keywords":["webpack","plugin","offline","cache","service-worker","serviceworker","appcache","application cache"],"devDependencies":{"babel":"^5.8.23"},"gitHead":"933e775d9c10b8342ff73c149d44b5cd9e07b1f3","_id":"offline-plugin@2.1.0","_shasum":"a5b1c4bd07fc853596ddd31d82b737e11082fe03","_from":".","_npmVersion":"2.14.7","_nodeVersion":"4.2.2","_npmUser":{"name":"nekr","email":"nekr.fabula@gmail.com"},"dist":{"shasum":"a5b1c4bd07fc853596ddd31d82b737e11082fe03","tarball":"https://registry.npmjs.org/offline-plugin/-/offline-plugin-2.1.0.tgz"},"maintainers":[{"name":"nekr","email":"nekr.fabula@gmail.com"}],"_npmOperationalInternal":{"host":"packages-12-west.internal.npmjs.com","tmp":"tmp/offline-plugin-2.1.0.tgz_1459623323805_0.775106244487688"},"directories":{}},"3.0.0":{"name":"offline-plugin","version":"3.0.0","description":"offline-plugin for webpack","main":"lib/index.js","files":["lib/","tpls/","runtime.js","empty-entry.js"],"scripts":{"test":"node tests/run","build":"babel src/ -d lib/","watch":"npm run build -- --watch"},"repository":{"type":"git","url":"git+https://github.com/NekR/offline-plugin.git"},"author":{"name":"Arthur Stolyar","email":"nekr.fabula@gmail.com"},"license":"MIT","dependencies":{"deep-extend":"^0.4.0","ejs":"^2.3.4","es6-promise":"^3.0.2","loader-utils":"0.2.x","minimatch":"^2.0.10","sw-cache-options":"^1.0.0"},"bugs":{"url":"https://github.com/NekR/offline-plugin/issues"},"homepage":"https://github.com/NekR/offline-plugin","keywords":["webpack","plugin","offline","cache","service-worker","serviceworker","appcache","application cache"],"devDependencies":{"babel":"^5.8.23","webpack":"^1.0.0","es6-promise":"^3.0.2"},"peerDependencies":{"webpack":">=1.0.0"},"gitHead":"c7548083611ccc226d4aa32fc0fe4bb63064edaf","_id":"offline-plugin@3.0.0","_shasum":"ba67dbde13205cf01e3e25ddec1c5f82458b3b76","_from":".","_npmVersion":"2.14.7","_nodeVersion":"4.2.2","_npmUser":{"name":"nekr","email":"nekr.fabula@gmail.com"},"dist":{"shasum":"ba67dbde13205cf01e3e25ddec1c5f82458b3b76","tarball":"https://registry.npmjs.org/offline-plugin/-/offline-plugin-3.0.0.tgz"},"maintainers":[{"name":"nekr","email":"nekr.fabula@gmail.com"}],"_npmOperationalInternal":{"host":"packages-12-west.internal.npmjs.com","tmp":"tmp/offline-plugin-3.0.0.tgz_1460054859531_0.47897442639805377"},"directories":{}},"3.0.1":{"name":"offline-plugin","version":"3.0.1","description":"offline-plugin for webpack","main":"lib/index.js","files":["lib/","tpls/","runtime.js","empty-entry.js"],"scripts":{"test":"node tests/run","build":"babel src/ -d lib/","watch":"npm run build -- --watch"},"repository":{"type":"git","url":"git+https://github.com/NekR/offline-plugin.git"},"author":{"name":"Arthur Stolyar","email":"nekr.fabula@gmail.com"},"license":"MIT","dependencies":{"deep-extend":"^0.4.0","ejs":"^2.3.4","es6-promise":"^3.0.2","loader-utils":"0.2.x","minimatch":"^2.0.10","sw-cache-options":"^1.0.0"},"bugs":{"url":"https://github.com/NekR/offline-plugin/issues"},"homepage":"https://github.com/NekR/offline-plugin","keywords":["webpack","plugin","offline","cache","service-worker","serviceworker","appcache","application cache"],"devDependencies":{"babel":"^5.8.23","webpack":"^1.0.0","es6-promise":"^3.0.2"},"peerDependencies":{"webpack":">=1.0.0"},"gitHead":"6a5b115edaf6641dd4d0b3b336c7bc809757f3e7","_id":"offline-plugin@3.0.1","_shasum":"c1c659f8396875a2ac304f30b7dac26ff5258dc8","_from":".","_npmVersion":"2.14.7","_nodeVersion":"4.2.2","_npmUser":{"name":"nekr","email":"nekr.fabula@gmail.com"},"dist":{"shasum":"c1c659f8396875a2ac304f30b7dac26ff5258dc8","tarball":"https://registry.npmjs.org/offline-plugin/-/offline-plugin-3.0.1.tgz"},"maintainers":[{"name":"nekr","email":"nekr.fabula@gmail.com"}],"_npmOperationalInternal":{"host":"packages-12-west.internal.npmjs.com","tmp":"tmp/offline-plugin-3.0.1.tgz_1460101408403_0.8599131556693465"},"directories":{}},"2.1.1":{"name":"offline-plugin","version":"2.1.1","description":"offline-plugin for webpack","main":"lib/index.js","files":["lib/","tpls/","runtime.js","empty-entry.js"],"scripts":{"test":"echo \"Error: no test specified\" && exit 1","build":"babel src/ -d lib/","watch":"npm run build -- --watch"},"repository":{"type":"git","url":"git+https://github.com/NekR/offline-plugin.git"},"author":{"name":"Arthur Stolyar","email":"nekr.fabula@gmail.com"},"license":"MIT","dependencies":{"deep-extend":"^0.4.0","ejs":"^2.3.4","es6-promise":"^3.0.2","loader-utils":"0.2.x","minimatch":"^2.0.10","serviceworker-cache-polyfill":"^3.0.0"},"bugs":{"url":"https://github.com/NekR/offline-plugin/issues"},"homepage":"https://github.com/NekR/offline-plugin","keywords":["webpack","plugin","offline","cache","service-worker","serviceworker","appcache","application cache"],"devDependencies":{"babel":"^5.8.23"},"gitHead":"16f4f8d54c58482e78c724d9d8b4d1593dda2205","_id":"offline-plugin@2.1.1","_shasum":"c3790f602d0874a2dcb664c8f7dc079ac01a3ee5","_from":".","_npmVersion":"2.14.7","_nodeVersion":"4.2.2","_npmUser":{"name":"nekr","email":"nekr.fabula@gmail.com"},"dist":{"shasum":"c3790f602d0874a2dcb664c8f7dc079ac01a3ee5","tarball":"https://registry.npmjs.org/offline-plugin/-/offline-plugin-2.1.1.tgz"},"maintainers":[{"name":"nekr","email":"nekr.fabula@gmail.com"}],"_npmOperationalInternal":{"host":"packages-16-east.internal.npmjs.com","tmp":"tmp/offline-plugin-2.1.1.tgz_1461318506074_0.4471870567649603"},"directories":{}},"3.1.0":{"name":"offline-plugin","version":"3.1.0","description":"offline-plugin for webpack","main":"lib/index.js","files":["lib/","tpls/","runtime.js","empty-entry.js"],"scripts":{"test":"node tests/run","build":"babel src/ -d lib/","watch":"npm run build -- --watch"},"repository":{"type":"git","url":"git+https://github.com/NekR/offline-plugin.git"},"author":{"name":"Arthur Stolyar","email":"nekr.fabula@gmail.com"},"license":"MIT","dependencies":{"deep-extend":"^0.4.0","ejs":"^2.3.4","es6-promise":"^3.0.2","loader-utils":"0.2.x","minimatch":"^2.0.10","sw-cache-options":"^1.0.0"},"bugs":{"url":"https://github.com/NekR/offline-plugin/issues"},"homepage":"https://github.com/NekR/offline-plugin","keywords":["webpack","plugin","offline","cache","service-worker","serviceworker","appcache","application cache"],"devDependencies":{"babel":"^5.8.23","webpack":"^1.0.0","es6-promise":"^3.0.2"},"peerDependencies":{"webpack":">=1.0.0"},"gitHead":"0a4779286a72914d5e7eb88945fea8f7531ffbdf","_id":"offline-plugin@3.1.0","_shasum":"81e03843aa80ef6572e487377167b37f099a2614","_from":".","_npmVersion":"2.14.7","_nodeVersion":"4.2.2","_npmUser":{"name":"nekr","email":"nekr.fabula@gmail.com"},"dist":{"shasum":"81e03843aa80ef6572e487377167b37f099a2614","tarball":"https://registry.npmjs.org/offline-plugin/-/offline-plugin-3.1.0.tgz"},"maintainers":[{"name":"nekr","email":"nekr.fabula@gmail.com"}],"_npmOperationalInternal":{"host":"packages-16-east.internal.npmjs.com","tmp":"tmp/offline-plugin-3.1.0.tgz_1461608991307_0.388291483046487"},"directories":{}},"3.1.1":{"name":"offline-plugin","version":"3.1.1","description":"offline-plugin for webpack","main":"lib/index.js","files":["lib/","tpls/","runtime.js","empty-entry.js"],"scripts":{"test":"node tests/run","build":"babel src/ -d lib/","watch":"npm run build -- --watch"},"repository":{"type":"git","url":"git+https://github.com/NekR/offline-plugin.git"},"author":{"name":"Arthur Stolyar","email":"nekr.fabula@gmail.com"},"license":"MIT","dependencies":{"deep-extend":"^0.4.0","ejs":"^2.3.4","es6-promise":"^3.0.2","loader-utils":"0.2.x","minimatch":"^2.0.10","sw-cache-options":"^1.0.0"},"bugs":{"url":"https://github.com/NekR/offline-plugin/issues"},"homepage":"https://github.com/NekR/offline-plugin","keywords":["webpack","plugin","offline","cache","service-worker","serviceworker","appcache","application cache"],"devDependencies":{"babel":"^5.8.23","webpack":"^1.0.0","es6-promise":"^3.0.2"},"peerDependencies":{"webpack":">=1.0.0"},"gitHead":"90205584c78aecfb75215cc57df8f624b0820add","_id":"offline-plugin@3.1.1","_shasum":"080d4054d1c1ab0af3f0d3fc99e28b67c93ed101","_from":".","_npmVersion":"2.14.7","_nodeVersion":"4.2.2","_npmUser":{"name":"nekr","email":"nekr.fabula@gmail.com"},"dist":{"shasum":"080d4054d1c1ab0af3f0d3fc99e28b67c93ed101","tarball":"https://registry.npmjs.org/offline-plugin/-/offline-plugin-3.1.1.tgz"},"maintainers":[{"name":"nekr","email":"nekr.fabula@gmail.com"}],"_npmOperationalInternal":{"host":"packages-12-west.internal.npmjs.com","tmp":"tmp/offline-plugin-3.1.1.tgz_1461713118028_0.06634310889057815"},"directories":{}},"2.2.0":{"name":"offline-plugin","version":"2.2.0","description":"offline-plugin for webpack","main":"lib/index.js","files":["lib/","tpls/","runtime.js","empty-entry.js"],"scripts":{"test":"echo \"Error: no test specified\" && exit 1","build":"babel src/ -d lib/","watch":"npm run build -- --watch"},"repository":{"type":"git","url":"git+https://github.com/NekR/offline-plugin.git"},"author":{"name":"Arthur Stolyar","email":"nekr.fabula@gmail.com"},"license":"MIT","dependencies":{"deep-extend":"^0.4.0","ejs":"^2.3.4","es6-promise":"^3.0.2","loader-utils":"0.2.x","minimatch":"^2.0.10","serviceworker-cache-polyfill":"^3.0.0"},"bugs":{"url":"https://github.com/NekR/offline-plugin/issues"},"homepage":"https://github.com/NekR/offline-plugin","keywords":["webpack","plugin","offline","cache","service-worker","serviceworker","appcache","application cache"],"devDependencies":{"babel":"^5.8.23"},"gitHead":"2efc6c36fae47f296e9da0324e8c960d08cdb224","_id":"offline-plugin@2.2.0","_shasum":"ac792fa4e24e395580918765eec1df617369cd3f","_from":".","_npmVersion":"2.14.7","_nodeVersion":"4.2.2","_npmUser":{"name":"nekr","email":"nekr.fabula@gmail.com"},"dist":{"shasum":"ac792fa4e24e395580918765eec1df617369cd3f","tarball":"https://registry.npmjs.org/offline-plugin/-/offline-plugin-2.2.0.tgz"},"maintainers":[{"name":"nekr","email":"nekr.fabula@gmail.com"}],"_npmOperationalInternal":{"host":"packages-16-east.internal.npmjs.com","tmp":"tmp/offline-plugin-2.2.0.tgz_1461713279569_0.6480594428721815"},"directories":{}},"2.2.1":{"name":"offline-plugin","version":"2.2.1","description":"offline-plugin for webpack","main":"lib/index.js","files":["lib/","tpls/","runtime.js","empty-entry.js"],"scripts":{"test":"echo \"Error: no test specified\" && exit 1","build":"babel src/ -d lib/","watch":"npm run build -- --watch"},"repository":{"type":"git","url":"git+https://github.com/NekR/offline-plugin.git"},"author":{"name":"Arthur Stolyar","email":"nekr.fabula@gmail.com"},"license":"MIT","dependencies":{"deep-extend":"^0.4.0","ejs":"^2.3.4","es6-promise":"^3.0.2","loader-utils":"0.2.x","minimatch":"^2.0.10","serviceworker-cache-polyfill":"^3.0.0"},"bugs":{"url":"https://github.com/NekR/offline-plugin/issues"},"homepage":"https://github.com/NekR/offline-plugin","keywords":["webpack","plugin","offline","cache","service-worker","serviceworker","appcache","application cache"],"devDependencies":{"babel":"^5.8.23"},"gitHead":"2d15d0d3971876039cd88541ba3e21851e895ac5","_id":"offline-plugin@2.2.1","_shasum":"706c7190a76472823f41e99c5fd94e3e1d1537fd","_from":".","_npmVersion":"2.14.7","_nodeVersion":"4.2.2","_npmUser":{"name":"nekr","email":"nekr.fabula@gmail.com"},"dist":{"shasum":"706c7190a76472823f41e99c5fd94e3e1d1537fd","tarball":"https://registry.npmjs.org/offline-plugin/-/offline-plugin-2.2.1.tgz"},"maintainers":[{"name":"nekr","email":"nekr.fabula@gmail.com"}],"_npmOperationalInternal":{"host":"packages-16-east.internal.npmjs.com","tmp":"tmp/offline-plugin-2.2.1.tgz_1462622282264_0.7782742728013545"},"directories":{}},"3.2.0":{"name":"offline-plugin","version":"3.2.0","description":"offline-plugin for webpack","main":"lib/index.js","files":["lib/","tpls/","runtime.js","empty-entry.js"],"scripts":{"test":"node tests/run","build":"babel src/ -d lib/","watch":"npm run build -- --watch"},"repository":{"type":"git","url":"git+https://github.com/NekR/offline-plugin.git"},"author":{"name":"Arthur Stolyar","email":"nekr.fabula@gmail.com"},"license":"MIT","dependencies":{"deep-extend":"^0.4.0","ejs":"^2.3.4","es6-promise":"^3.0.2","loader-utils":"0.2.x","minimatch":"^2.0.10"},"bugs":{"url":"https://github.com/NekR/offline-plugin/issues"},"homepage":"https://github.com/NekR/offline-plugin","keywords":["webpack","plugin","offline","cache","service-worker","serviceworker","appcache","application cache"],"devDependencies":{"babel":"^5.8.23","webpack":"^1.0.0","es6-promise":"^3.0.2"},"peerDependencies":{"webpack":">=1.0.0"},"gitHead":"3c0375122079980f6cca6cf96180aa6f39384d7f","_id":"offline-plugin@3.2.0","_shasum":"e2467fb3272d7ecead73acb627adedaa239e7e36","_from":".","_npmVersion":"2.14.7","_nodeVersion":"4.2.2","_npmUser":{"name":"nekr","email":"nekr.fabula@gmail.com"},"dist":{"shasum":"e2467fb3272d7ecead73acb627adedaa239e7e36","tarball":"https://registry.npmjs.org/offline-plugin/-/offline-plugin-3.2.0.tgz"},"maintainers":[{"name":"nekr","email":"nekr.fabula@gmail.com"}],"_npmOperationalInternal":{"host":"packages-16-east.internal.npmjs.com","tmp":"tmp/offline-plugin-3.2.0.tgz_1462667505716_0.39472877397201955"},"directories":{}},"3.2.1":{"name":"offline-plugin","version":"3.2.1","description":"offline-plugin for webpack","main":"lib/index.js","files":["lib/","tpls/","runtime.js","empty-entry.js"],"scripts":{"test":"node tests/run","build":"babel src/ -d lib/","watch":"npm run build -- --watch"},"repository":{"type":"git","url":"git+https://github.com/NekR/offline-plugin.git"},"author":{"name":"Arthur Stolyar","email":"nekr.fabula@gmail.com"},"license":"MIT","dependencies":{"deep-extend":"^0.4.0","ejs":"^2.3.4","es6-promise":"^3.0.2","loader-utils":"0.2.x","minimatch":"^2.0.10"},"bugs":{"url":"https://github.com/NekR/offline-plugin/issues"},"homepage":"https://github.com/NekR/offline-plugin","keywords":["webpack","plugin","offline","cache","service-worker","serviceworker","appcache","application cache"],"devDependencies":{"babel":"^5.8.23","webpack":"^1.0.0","es6-promise":"^3.0.2"},"peerDependencies":{"webpack":">=1.0.0"},"gitHead":"fc108ccf53b03712e8de460e0114a86486ac942e","_id":"offline-plugin@3.2.1","_shasum":"ca1e9288df3243242b97111e3b72fcc0bdad63e0","_from":".","_npmVersion":"2.14.7","_nodeVersion":"4.2.2","_npmUser":{"name":"nekr","email":"nekr.fabula@gmail.com"},"dist":{"shasum":"ca1e9288df3243242b97111e3b72fcc0bdad63e0","tarball":"https://registry.npmjs.org/offline-plugin/-/offline-plugin-3.2.1.tgz"},"maintainers":[{"name":"nekr","email":"nekr.fabula@gmail.com"}],"_npmOperationalInternal":{"host":"packages-12-west.internal.npmjs.com","tmp":"tmp/offline-plugin-3.2.1.tgz_1462784266389_0.3056518647354096"},"directories":{}},"3.3.0":{"name":"offline-plugin","version":"3.3.0","description":"offline-plugin for webpack","main":"lib/index.js","files":["lib/","tpls/","runtime.js","empty-entry.js"],"scripts":{"test":"node tests/run","build":"babel src/ -d lib/","watch":"npm run build -- --watch"},"repository":{"type":"git","url":"git+https://github.com/NekR/offline-plugin.git"},"author":{"name":"Arthur Stolyar","email":"nekr.fabula@gmail.com"},"license":"MIT","dependencies":{"deep-extend":"^0.4.0","ejs":"^2.3.4","es6-promise":"^3.0.2","loader-utils":"0.2.x","minimatch":"^2.0.10"},"bugs":{"url":"https://github.com/NekR/offline-plugin/issues"},"homepage":"https://github.com/NekR/offline-plugin","keywords":["webpack","plugin","offline","cache","service-worker","serviceworker","appcache","application cache"],"devDependencies":{"babel":"^5.8.23","webpack":"^1.0.0","es6-promise":"^3.0.2"},"peerDependencies":{"webpack":">=1.0.0"},"gitHead":"8b3f1cfa743968d986ccab719a647b73e9d48653","_id":"offline-plugin@3.3.0","_shasum":"7ce027fe4d5959aca2a5b0cc2e1b8cfabef4dda4","_from":".","_npmVersion":"2.14.7","_nodeVersion":"4.2.2","_npmUser":{"name":"nekr","email":"nekr.fabula@gmail.com"},"dist":{"shasum":"7ce027fe4d5959aca2a5b0cc2e1b8cfabef4dda4","tarball":"https://registry.npmjs.org/offline-plugin/-/offline-plugin-3.3.0.tgz"},"maintainers":[{"name":"nekr","email":"nekr.fabula@gmail.com"}],"_npmOperationalInternal":{"host":"packages-16-east.internal.npmjs.com","tmp":"tmp/offline-plugin-3.3.0.tgz_1465025314341_0.45504525140859187"},"directories":{}},"3.3.1":{"name":"offline-plugin","version":"3.3.1","description":"offline-plugin for webpack","main":"lib/index.js","files":["lib/","tpls/","runtime.js","empty-entry.js"],"scripts":{"test":"node tests/run","build":"babel src/ -d lib/","watch":"npm run build -- --watch"},"repository":{"type":"git","url":"git+https://github.com/NekR/offline-plugin.git"},"author":{"name":"Arthur Stolyar","email":"nekr.fabula@gmail.com"},"license":"MIT","dependencies":{"deep-extend":"^0.4.0","ejs":"^2.3.4","es6-promise":"^3.0.2","loader-utils":"0.2.x","minimatch":"^2.0.10"},"bugs":{"url":"https://github.com/NekR/offline-plugin/issues"},"homepage":"https://github.com/NekR/offline-plugin","keywords":["webpack","plugin","offline","cache","service-worker","serviceworker","appcache","application cache"],"devDependencies":{"babel":"^5.8.23","webpack":"^1.0.0","es6-promise":"^3.0.2"},"gitHead":"ac35022204b7ae66caed7c45fac64ab341cd8cfd","_id":"offline-plugin@3.3.1","_shasum":"d52fbf732ccf0013198165d38b0b35e583ec7f15","_from":".","_npmVersion":"2.14.7","_nodeVersion":"4.2.2","_npmUser":{"name":"nekr","email":"nekr.fabula@gmail.com"},"dist":{"shasum":"d52fbf732ccf0013198165d38b0b35e583ec7f15","tarball":"https://registry.npmjs.org/offline-plugin/-/offline-plugin-3.3.1.tgz"},"maintainers":[{"name":"nekr","email":"nekr.fabula@gmail.com"}],"_npmOperationalInternal":{"host":"packages-16-east.internal.npmjs.com","tmp":"tmp/offline-plugin-3.3.1.tgz_1465452293497_0.970742961158976"},"directories":{}},"3.4.0":{"name":"offline-plugin","version":"3.4.0","description":"offline-plugin for webpack","main":"lib/index.js","files":["lib/","tpls/","runtime.js","empty-entry.js"],"scripts":{"test":"node tests/run","build":"babel src/ -d lib/","watch":"npm run build -- --watch"},"repository":{"type":"git","url":"git+https://github.com/NekR/offline-plugin.git"},"author":{"name":"Arthur Stolyar","email":"nekr.fabula@gmail.com"},"license":"MIT","dependencies":{"deep-extend":"^0.4.0","ejs":"^2.3.4","es6-promise":"^3.0.2","loader-utils":"0.2.x","minimatch":"^2.0.10"},"bugs":{"url":"https://github.com/NekR/offline-plugin/issues"},"homepage":"https://github.com/NekR/offline-plugin","keywords":["webpack","plugin","offline","cache","service-worker","serviceworker","appcache","application cache"],"devDependencies":{"babel":"^5.8.23","webpack":"^1.0.0","es6-promise":"^3.0.2"},"gitHead":"743a14d0201253bad46bd982858821abac444220","_id":"offline-plugin@3.4.0","_shasum":"4bea942c65de66fe0fe03281057efba21a604854","_from":".","_npmVersion":"2.14.7","_nodeVersion":"4.2.2","_npmUser":{"name":"nekr","email":"nekr.fabula@gmail.com"},"dist":{"shasum":"4bea942c65de66fe0fe03281057efba21a604854","tarball":"https://registry.npmjs.org/offline-plugin/-/offline-plugin-3.4.0.tgz"},"maintainers":[{"name":"nekr","email":"nekr.fabula@gmail.com"}],"_npmOperationalInternal":{"host":"packages-12-west.internal.npmjs.com","tmp":"tmp/offline-plugin-3.4.0.tgz_1466144923846_0.9535741577856243"},"directories":{}},"3.4.1":{"name":"offline-plugin","version":"3.4.1","description":"offline-plugin for webpack","main":"lib/index.js","files":["lib/","tpls/","runtime.js","empty-entry.js"],"scripts":{"test":"node tests/run","build":"babel src/ -d lib/","watch":"npm run build -- --watch"},"repository":{"type":"git","url":"git+https://github.com/NekR/offline-plugin.git"},"author":{"name":"Arthur Stolyar","email":"nekr.fabula@gmail.com"},"license":"MIT","dependencies":{"deep-extend":"^0.4.0","ejs":"^2.3.4","es6-promise":"^3.0.2","loader-utils":"0.2.x","minimatch":"^3.0.2"},"bugs":{"url":"https://github.com/NekR/offline-plugin/issues"},"homepage":"https://github.com/NekR/offline-plugin","keywords":["webpack","plugin","offline","cache","service-worker","serviceworker","appcache","application cache"],"devDependencies":{"babel":"^5.8.23","webpack":"^1.0.0","es6-promise":"^3.0.2"},"gitHead":"8a6aa98da95db7aa6fbcb8eb9336bd5f7423725d","_id":"offline-plugin@3.4.1","_shasum":"c0d2618779980216f442e75d00922c47f31726a1","_from":".","_npmVersion":"3.9.5","_nodeVersion":"6.2.2","_npmUser":{"name":"nekr","email":"nekr.fabula@gmail.com"},"dist":{"shasum":"c0d2618779980216f442e75d00922c47f31726a1","tarball":"https://registry.npmjs.org/offline-plugin/-/offline-plugin-3.4.1.tgz"},"maintainers":[{"name":"nekr","email":"nekr.fabula@gmail.com"}],"_npmOperationalInternal":{"host":"packages-12-west.internal.npmjs.com","tmp":"tmp/offline-plugin-3.4.1.tgz_1467291283501_0.6570072416216135"},"directories":{}},"3.4.2":{"name":"offline-plugin","version":"3.4.2","description":"offline-plugin for webpack","main":"lib/index.js","files":["lib/","tpls/","runtime.js","empty-entry.js"],"scripts":{"test":"node tests/run","build":"babel src/ -d lib/","watch":"npm run build -- --watch"},"repository":{"type":"git","url":"git+https://github.com/NekR/offline-plugin.git"},"author":{"name":"Arthur Stolyar","email":"nekr.fabula@gmail.com"},"license":"MIT","dependencies":{"deep-extend":"^0.4.0","ejs":"^2.3.4","es6-promise":"^3.0.2","loader-utils":"0.2.x","minimatch":"^3.0.2"},"bugs":{"url":"https://github.com/NekR/offline-plugin/issues"},"homepage":"https://github.com/NekR/offline-plugin","keywords":["webpack","plugin","offline","cache","service-worker","serviceworker","appcache","application cache"],"devDependencies":{"babel":"^5.8.23","webpack":"^1.0.0","es6-promise":"^3.0.2"},"gitHead":"51f7728f85637cd770ca0cb8f506b92ce5eca16a","_id":"offline-plugin@3.4.2","_shasum":"ddbb9eec3e8fd052ec51e03c56afdc33b0a331a2","_from":".","_npmVersion":"3.9.5","_nodeVersion":"6.2.2","_npmUser":{"name":"nekr","email":"nekr.fabula@gmail.com"},"dist":{"shasum":"ddbb9eec3e8fd052ec51e03c56afdc33b0a331a2","tarball":"https://registry.npmjs.org/offline-plugin/-/offline-plugin-3.4.2.tgz"},"maintainers":[{"name":"nekr","email":"nekr.fabula@gmail.com"}],"_npmOperationalInternal":{"host":"packages-12-west.internal.npmjs.com","tmp":"tmp/offline-plugin-3.4.2.tgz_1468243640974_0.764546503778547"},"directories":{}},"4.0.0":{"name":"offline-plugin","version":"4.0.0","description":"offline-plugin for webpack","main":"lib/index.js","files":["lib/","tpls/","runtime.js","empty-entry.js"],"scripts":{"test":"node tests/run","build":"babel src/ -d lib/","watch":"npm run build -- --watch"},"repository":{"type":"git","url":"git+https://github.com/NekR/offline-plugin.git"},"author":{"name":"Arthur Stolyar","email":"nekr.fabula@gmail.com"},"license":"MIT","dependencies":{"deep-extend":"^0.4.0","ejs":"^2.3.4","es6-promise":"^3.0.2","loader-utils":"0.2.x","minimatch":"^3.0.2"},"bugs":{"url":"https://github.com/NekR/offline-plugin/issues"},"homepage":"https://github.com/NekR/offline-plugin","keywords":["webpack","plugin","offline","cache","service-worker","serviceworker","appcache","application cache"],"devDependencies":{"babel":"^5.8.23","webpack":"^1.0.0","es6-promise":"^3.0.2"},"gitHead":"d45e2752816d791fae824efef135bced32d4e5d6","_id":"offline-plugin@4.0.0","_shasum":"68373acbae9bec3b46ab001239267fc76ad6d577","_from":".","_npmVersion":"3.9.5","_nodeVersion":"6.2.2","_npmUser":{"name":"nekr","email":"nekr.fabula@gmail.com"},"dist":{"shasum":"68373acbae9bec3b46ab001239267fc76ad6d577","tarball":"https://registry.npmjs.org/offline-plugin/-/offline-plugin-4.0.0.tgz"},"maintainers":[{"name":"nekr","email":"nekr.fabula@gmail.com"}],"_npmOperationalInternal":{"host":"packages-16-east.internal.npmjs.com","tmp":"tmp/offline-plugin-4.0.0.tgz_1468935123786_0.7229462489485741"},"directories":{}},"4.1.0":{"name":"offline-plugin","version":"4.1.0","description":"offline-plugin for webpack","main":"lib/index.js","files":["lib/","tpls/","runtime.js","empty-entry.js"],"scripts":{"test":"node tests/legacy/run","build":"babel src/ -d lib/","watch":"npm run build -- --watch"},"repository":{"type":"git","url":"git+https://github.com/NekR/offline-plugin.git"},"author":{"name":"Arthur Stolyar","email":"nekr.fabula@gmail.com"},"license":"MIT","dependencies":{"deep-extend":"^0.4.0","ejs":"^2.3.4","es6-promise":"^3.0.2","loader-utils":"0.2.x","minimatch":"^3.0.2"},"bugs":{"url":"https://github.com/NekR/offline-plugin/issues"},"homepage":"https://github.com/NekR/offline-plugin","keywords":["webpack","plugin","offline","cache","service-worker","serviceworker","appcache","application cache"],"devDependencies":{"babel":"^5.8.23","dir-compare":"^1.1.0","es6-promise":"^3.0.2","on-build-webpack":"^0.1.0","webpack":"^1.0.0"},"gitHead":"2412a35f23097b9be3498ca9dfb130bd03d765c0","_id":"offline-plugin@4.1.0","_shasum":"646d71192b983bc71a034d1772a5fa700702c8e3","_from":".","_npmVersion":"3.9.5","_nodeVersion":"6.2.2","_npmUser":{"name":"nekr","email":"nekr.fabula@gmail.com"},"dist":{"shasum":"646d71192b983bc71a034d1772a5fa700702c8e3","tarball":"https://registry.npmjs.org/offline-plugin/-/offline-plugin-4.1.0.tgz"},"maintainers":[{"name":"nekr","email":"nekr.fabula@gmail.com"}],"_npmOperationalInternal":{"host":"packages-16-east.internal.npmjs.com","tmp":"tmp/offline-plugin-4.1.0.tgz_1472683189411_0.5650396493729204"},"directories":{}},"4.2.0":{"name":"offline-plugin","version":"4.2.0","description":"offline-plugin for webpack","main":"lib/index.js","files":["lib/","tpls/","runtime.js","empty-entry.js"],"scripts":{"test":"node tests/legacy/run","build":"babel src/ -d lib/","watch":"npm run build -- --watch"},"repository":{"type":"git","url":"git+https://github.com/NekR/offline-plugin.git"},"author":{"name":"Arthur Stolyar","email":"nekr.fabula@gmail.com"},"license":"MIT","dependencies":{"deep-extend":"^0.4.0","ejs":"^2.3.4","es6-promise":"^3.0.2","loader-utils":"0.2.x","minimatch":"^3.0.2"},"bugs":{"url":"https://github.com/NekR/offline-plugin/issues"},"homepage":"https://github.com/NekR/offline-plugin","keywords":["webpack","plugin","offline","cache","service-worker","serviceworker","appcache","application cache"],"devDependencies":{"babel":"^5.8.23","dir-compare":"^1.1.0","es6-promise":"^3.0.2","on-build-webpack":"^0.1.0","webpack":"^1.0.0"},"gitHead":"34feaabfd26fef4437ddf7334ecca2a87eaa7968","_id":"offline-plugin@4.2.0","_shasum":"e051c3a70bc284c49da19a03119522865c067778","_from":".","_npmVersion":"3.9.5","_nodeVersion":"6.2.2","_npmUser":{"name":"nekr","email":"nekr.fabula@gmail.com"},"dist":{"shasum":"e051c3a70bc284c49da19a03119522865c067778","tarball":"https://registry.npmjs.org/offline-plugin/-/offline-plugin-4.2.0.tgz"},"maintainers":[{"name":"nekr","email":"nekr.fabula@gmail.com"}],"_npmOperationalInternal":{"host":"packages-12-west.internal.npmjs.com","tmp":"tmp/offline-plugin-4.2.0.tgz_1475487041448_0.845902394503355"},"directories":{}},"4.2.1":{"name":"offline-plugin","version":"4.2.1","description":"offline-plugin for webpack","main":"lib/index.js","files":["lib/","tpls/","runtime.js","empty-entry.js"],"scripts":{"test":"node tests/legacy/run","build":"babel src/ -d lib/","watch":"npm run build -- --watch"},"repository":{"type":"git","url":"git+https://github.com/NekR/offline-plugin.git"},"author":{"name":"Arthur Stolyar","email":"nekr.fabula@gmail.com"},"license":"MIT","dependencies":{"deep-extend":"^0.4.0","ejs":"^2.3.4","es6-promise":"^3.0.2","loader-utils":"0.2.x","minimatch":"^3.0.2"},"bugs":{"url":"https://github.com/NekR/offline-plugin/issues"},"homepage":"https://github.com/NekR/offline-plugin","keywords":["webpack","plugin","offline","cache","service-worker","serviceworker","appcache","application cache"],"devDependencies":{"babel":"^5.8.23","dir-compare":"^1.1.0","es6-promise":"^3.0.2","on-build-webpack":"^0.1.0","webpack":"^1.0.0"},"gitHead":"e0404874f99d85e8a20716feb250125614c21eaa","_id":"offline-plugin@4.2.1","_shasum":"d4e981991ad9a23f202e6dc8cc1783184f7d7f63","_from":".","_npmVersion":"3.9.5","_nodeVersion":"6.2.2","_npmUser":{"name":"nekr","email":"nekr.fabula@gmail.com"},"dist":{"shasum":"d4e981991ad9a23f202e6dc8cc1783184f7d7f63","tarball":"https://registry.npmjs.org/offline-plugin/-/offline-plugin-4.2.1.tgz"},"maintainers":[{"name":"nekr","email":"nekr.fabula@gmail.com"}],"_npmOperationalInternal":{"host":"packages-12-west.internal.npmjs.com","tmp":"tmp/offline-plugin-4.2.1.tgz_1475581465486_0.8545858750585467"},"directories":{}},"4.3.0":{"name":"offline-plugin","version":"4.3.0","description":"offline-plugin for webpack","main":"lib/index.js","files":["lib/","tpls/","runtime.js","empty-entry.js"],"scripts":{"test":"node tests/legacy/run","build":"babel src/ -d lib/","watch":"npm run build -- --watch"},"repository":{"type":"git","url":"git+https://github.com/NekR/offline-plugin.git"},"author":{"name":"Arthur Stolyar","email":"nekr.fabula@gmail.com"},"license":"MIT","dependencies":{"deep-extend":"^0.4.0","ejs":"^2.3.4","loader-utils":"0.2.x","minimatch":"^3.0.2","slash":"^1.0.0"},"bugs":{"url":"https://github.com/NekR/offline-plugin/issues"},"homepage":"https://github.com/NekR/offline-plugin","keywords":["webpack","plugin","offline","cache","service-worker","serviceworker","appcache","application cache"],"devDependencies":{"babel":"^5.8.23","chalk":"^1.1.3","cli-highlight":"^1.1.4","diff":"^3.0.1","dir-compare":"^1.1.0","minimatch":"^3.0.3","on-build-webpack":"^0.1.0","webpack":"^1.0.0"},"gitHead":"81a20b99e648dc5f107e22bc13ca59f57655bfb2","_id":"offline-plugin@4.3.0","_shasum":"5b1fa68c7dd8d76ac39b04612b16f5c3768ed71c","_from":".","_npmVersion":"3.10.3","_nodeVersion":"6.7.0","_npmUser":{"name":"nekr","email":"nekr.fabula@gmail.com"},"dist":{"shasum":"5b1fa68c7dd8d76ac39b04612b16f5c3768ed71c","tarball":"https://registry.npmjs.org/offline-plugin/-/offline-plugin-4.3.0.tgz"},"maintainers":[{"name":"nekr","email":"nekr.fabula@gmail.com"}],"_npmOperationalInternal":{"host":"packages-12-west.internal.npmjs.com","tmp":"tmp/offline-plugin-4.3.0.tgz_1476545122602_0.24497654009610415"},"directories":{}},"4.3.1":{"name":"offline-plugin","version":"4.3.1","description":"offline-plugin for webpack","main":"lib/index.js","files":["lib/","tpls/","runtime.js","empty-entry.js"],"scripts":{"test":"node tests/legacy/run","build":"babel src/ -d lib/","watch":"npm run build -- --watch","prepublish":"npm run build && npm run test"},"repository":{"type":"git","url":"git+https://github.com/NekR/offline-plugin.git"},"author":{"name":"Arthur Stolyar","email":"nekr.fabula@gmail.com"},"license":"MIT","dependencies":{"deep-extend":"^0.4.0","ejs":"^2.3.4","loader-utils":"0.2.x","minimatch":"^3.0.2","slash":"^1.0.0"},"bugs":{"url":"https://github.com/NekR/offline-plugin/issues"},"homepage":"https://github.com/NekR/offline-plugin","keywords":["webpack","plugin","offline","cache","service-worker","serviceworker","appcache","application cache"],"devDependencies":{"babel":"^5.8.23","chalk":"^1.1.3","cli-highlight":"^1.1.4","del":"^2.2.2","diff":"^3.0.1","dir-compare":"^1.1.0","minimatch":"^3.0.3","on-build-webpack":"^0.1.0","webpack":"^1.0.0"},"gitHead":"ab9584c91fb09762844c4c58a262d4e2213b66e6","_id":"offline-plugin@4.3.1","_shasum":"f30fb8feca6fe59cd2196ca79f771fdb12683be4","_from":".","_npmVersion":"3.10.3","_nodeVersion":"6.7.0","_npmUser":{"name":"nekr","email":"nekr.fabula@gmail.com"},"dist":{"shasum":"f30fb8feca6fe59cd2196ca79f771fdb12683be4","tarball":"https://registry.npmjs.org/offline-plugin/-/offline-plugin-4.3.1.tgz"},"maintainers":[{"name":"nekr","email":"nekr.fabula@gmail.com"}],"_npmOperationalInternal":{"host":"packages-12-west.internal.npmjs.com","tmp":"tmp/offline-plugin-4.3.1.tgz_1476557109309_0.6247948501259089"},"directories":{}},"4.4.0":{"name":"offline-plugin","version":"4.4.0","description":"offline-plugin for webpack","main":"lib/index.js","files":["lib/","tpls/","runtime.js","empty-entry.js"],"scripts":{"test":"node tests/legacy/run","build":"babel src/ -d lib/","watch":"npm run build -- --watch","install:build-deps":"node build/install.js"},"repository":{"type":"git","url":"git+https://github.com/NekR/offline-plugin.git"},"author":{"name":"Arthur Stolyar","email":"nekr.fabula@gmail.com"},"license":"MIT","dependencies":{"deep-extend":"^0.4.0","ejs":"^2.3.4","loader-utils":"0.2.x","minimatch":"^3.0.3","slash":"^1.0.0"},"bugs":{"url":"https://github.com/NekR/offline-plugin/issues"},"homepage":"https://github.com/NekR/offline-plugin","keywords":["webpack","plugin","offline","cache","service-worker","serviceworker","appcache","application cache"],"devDependencies":{"del":"^2.2.2","webpack":"^1.0.0","chalk":"^1.1.3","cli-highlight":"^1.1.4","diff":"^3.0.1","dir-compare":"^1.1.0","on-build-webpack":"^0.1.0"},"buildDependencies":{"babel":"^5.8.23"},"gitHead":"2ffacfb035083c62cda2699efef72bf4b275414e","_id":"offline-plugin@4.4.0","_shasum":"b710c4f52f87fee97d99871f0a7d11731c616da9","_from":".","_npmVersion":"3.9.5","_nodeVersion":"6.2.2","_npmUser":{"name":"nekr","email":"nekr.fabula@gmail.com"},"dist":{"shasum":"b710c4f52f87fee97d99871f0a7d11731c616da9","tarball":"https://registry.npmjs.org/offline-plugin/-/offline-plugin-4.4.0.tgz"},"maintainers":[{"name":"nekr","email":"nekr.fabula@gmail.com"}],"_npmOperationalInternal":{"host":"packages-18-east.internal.npmjs.com","tmp":"tmp/offline-plugin-4.4.0.tgz_1477141299542_0.7534211601596326"},"directories":{}},"4.4.1":{"name":"offline-plugin","version":"4.4.1","description":"offline-plugin for webpack","main":"lib/index.js","files":["lib/","tpls/","runtime.js","empty-entry.js"],"scripts":{"test":"node tests/legacy/run","build":"babel src/ -d lib/","watch":"npm run build -- --watch","install:build-deps":"node build/install.js"},"repository":{"type":"git","url":"git+https://github.com/NekR/offline-plugin.git"},"author":{"name":"Arthur Stolyar","email":"nekr.fabula@gmail.com"},"license":"MIT","dependencies":{"deep-extend":"^0.4.0","ejs":"^2.3.4","loader-utils":"0.2.x","minimatch":"^3.0.3","slash":"^1.0.0"},"bugs":{"url":"https://github.com/NekR/offline-plugin/issues"},"homepage":"https://github.com/NekR/offline-plugin","keywords":["webpack","plugin","offline","cache","service-worker","serviceworker","appcache","application cache"],"devDependencies":{"del":"^2.2.2","webpack":"^1.0.0","chalk":"^1.1.3","cli-highlight":"^1.1.4","diff":"^3.0.1","dir-compare":"^1.1.0","on-build-webpack":"^0.1.0"},"buildDependencies":{"babel":"^5.8.23"},"gitHead":"b9647d0483bd273c68d1ff3ed3583ee11ba1d7ca","_id":"offline-plugin@4.4.1","_shasum":"27cdac16ca7690b3ce9d3d0975f66a3c8f4a18db","_from":".","_npmVersion":"3.9.5","_nodeVersion":"6.2.2","_npmUser":{"name":"nekr","email":"nekr.fabula@gmail.com"},"dist":{"shasum":"27cdac16ca7690b3ce9d3d0975f66a3c8f4a18db","tarball":"https://registry.npmjs.org/offline-plugin/-/offline-plugin-4.4.1.tgz"},"maintainers":[{"name":"nekr","email":"nekr.fabula@gmail.com"}],"_npmOperationalInternal":{"host":"packages-12-west.internal.npmjs.com","tmp":"tmp/offline-plugin-4.4.1.tgz_1477499421070_0.4531870908103883"},"directories":{}},"4.5.0-beta":{"name":"offline-plugin","version":"4.5.0-beta","description":"offline-plugin for webpack","main":"lib/index.js","files":["lib/","tpls/","runtime.js","empty-entry.js"],"scripts":{"test":"node tests/legacy/run","build":"babel src/ -d lib/","watch":"npm run build -- --watch","install:build-deps":"node build/install.js"},"repository":{"type":"git","url":"git+https://github.com/NekR/offline-plugin.git"},"author":{"name":"Arthur Stolyar","email":"nekr.fabula@gmail.com"},"license":"MIT","dependencies":{"deep-extend":"^0.4.0","ejs":"^2.3.4","loader-utils":"0.2.x","minimatch":"^3.0.3","slash":"^1.0.0"},"bugs":{"url":"https://github.com/NekR/offline-plugin/issues"},"homepage":"https://github.com/NekR/offline-plugin","keywords":["webpack","plugin","offline","cache","service-worker","serviceworker","appcache","application cache"],"devDependencies":{"del":"^2.2.2","webpack":"^1.0.0","chalk":"^1.1.3","cli-highlight":"^1.1.4","diff":"^3.0.1","dir-compare":"^1.1.0","on-build-webpack":"^0.1.0"},"buildDependencies":{"babel":"^5.8.23"},"gitHead":"08db29ffd44442474026f034b2094a1c9d84bff7","_id":"offline-plugin@4.5.0-beta","_shasum":"45920aad7ae0b0202afe9192c192108711d82833","_from":".","_npmVersion":"3.10.3","_nodeVersion":"6.7.0","_npmUser":{"name":"nekr","email":"nekr.fabula@gmail.com"},"dist":{"shasum":"45920aad7ae0b0202afe9192c192108711d82833","tarball":"https://registry.npmjs.org/offline-plugin/-/offline-plugin-4.5.0-beta.tgz"},"maintainers":[{"name":"nekr","email":"nekr.fabula@gmail.com"}],"_npmOperationalInternal":{"host":"packages-12-west.internal.npmjs.com","tmp":"tmp/offline-plugin-4.5.0-beta.tgz_1479766341040_0.8380656607914716"},"directories":{}},"4.5.0-beta.1":{"name":"offline-plugin","version":"4.5.0-beta.1","description":"offline-plugin for webpack","main":"lib/index.js","files":["lib/","tpls/","runtime.js","empty-entry.js"],"scripts":{"test":"node tests/legacy/run","build":"babel src/ -d lib/","watch":"npm run build -- --watch","install:build-deps":"node build/install.js"},"repository":{"type":"git","url":"git+https://github.com/NekR/offline-plugin.git"},"author":{"name":"Arthur Stolyar","email":"nekr.fabula@gmail.com"},"license":"MIT","dependencies":{"deep-extend":"^0.4.0","ejs":"^2.3.4","loader-utils":"0.2.x","minimatch":"^3.0.3","slash":"^1.0.0"},"bugs":{"url":"https://github.com/NekR/offline-plugin/issues"},"homepage":"https://github.com/NekR/offline-plugin","keywords":["webpack","plugin","offline","cache","service-worker","serviceworker","appcache","application cache"],"devDependencies":{"del":"^2.2.2","webpack":"^1.0.0","chalk":"^1.1.3","cli-highlight":"^1.1.4","diff":"^3.0.1","dir-compare":"^1.1.0","on-build-webpack":"^0.1.0"},"buildDependencies":{"babel":"^5.8.23"},"gitHead":"76e82cfdc9eb65c0d0196c3c074aaea9a6bc8940","_id":"offline-plugin@4.5.0-beta.1","_shasum":"9d72500c6b0875a348407b3b760cdce36752c464","_from":".","_npmVersion":"3.10.3","_nodeVersion":"6.7.0","_npmUser":{"name":"nekr","email":"nekr.fabula@gmail.com"},"dist":{"shasum":"9d72500c6b0875a348407b3b760cdce36752c464","tarball":"https://registry.npmjs.org/offline-plugin/-/offline-plugin-4.5.0-beta.1.tgz"},"maintainers":[{"name":"nekr","email":"nekr.fabula@gmail.com"}],"_npmOperationalInternal":{"host":"packages-12-west.internal.npmjs.com","tmp":"tmp/offline-plugin-4.5.0-beta.1.tgz_1479819051313_0.252703147707507"},"directories":{}},"4.5.0-beta.2":{"name":"offline-plugin","version":"4.5.0-beta.2","description":"offline-plugin for webpack","main":"lib/index.js","files":["lib/","tpls/","runtime.js","empty-entry.js"],"scripts":{"test":"node tests/legacy/run","build":"babel src/ -d lib/","watch":"npm run build -- --watch","install:build-deps":"node build/install.js"},"repository":{"type":"git","url":"git+https://github.com/NekR/offline-plugin.git"},"author":{"name":"Arthur Stolyar","email":"nekr.fabula@gmail.com"},"license":"MIT","dependencies":{"deep-extend":"^0.4.0","ejs":"^2.3.4","loader-utils":"0.2.x","minimatch":"^3.0.3","slash":"^1.0.0"},"bugs":{"url":"https://github.com/NekR/offline-plugin/issues"},"homepage":"https://github.com/NekR/offline-plugin","keywords":["webpack","plugin","offline","cache","service-worker","serviceworker","appcache","application cache"],"devDependencies":{"del":"^2.2.2","webpack":"^1.0.0","chalk":"^1.1.3","cli-highlight":"^1.1.4","diff":"^3.0.1","dir-compare":"^1.1.0","on-build-webpack":"^0.1.0"},"buildDependencies":{"babel":"^5.8.23"},"gitHead":"0cda561b91d87a48e71aafe77a990d7561be1aff","_id":"offline-plugin@4.5.0-beta.2","_shasum":"1c49aa916653e62b7efa76a4b9dc912a4de3e616","_from":".","_npmVersion":"3.10.3","_nodeVersion":"6.7.0","_npmUser":{"name":"nekr","email":"nekr.fabula@gmail.com"},"dist":{"shasum":"1c49aa916653e62b7efa76a4b9dc912a4de3e616","tarball":"https://registry.npmjs.org/offline-plugin/-/offline-plugin-4.5.0-beta.2.tgz"},"maintainers":[{"name":"nekr","email":"nekr.fabula@gmail.com"}],"_npmOperationalInternal":{"host":"packages-18-east.internal.npmjs.com","tmp":"tmp/offline-plugin-4.5.0-beta.2.tgz_1479821525463_0.5988048252183944"},"directories":{}},"4.5.0-beta.3":{"name":"offline-plugin","version":"4.5.0-beta.3","description":"offline-plugin for webpack","main":"lib/index.js","files":["lib/","tpls/","runtime.js","empty-entry.js"],"scripts":{"test":"node tests/legacy/run","build":"babel src/ -d lib/","watch":"npm run build -- --watch","install:build-deps":"node build/install.js"},"repository":{"type":"git","url":"git+https://github.com/NekR/offline-plugin.git"},"author":{"name":"Arthur Stolyar","email":"nekr.fabula@gmail.com"},"license":"MIT","dependencies":{"deep-extend":"^0.4.0","ejs":"^2.3.4","loader-utils":"0.2.x","minimatch":"^3.0.3","slash":"^1.0.0"},"bugs":{"url":"https://github.com/NekR/offline-plugin/issues"},"homepage":"https://github.com/NekR/offline-plugin","keywords":["webpack","plugin","offline","cache","service-worker","serviceworker","appcache","application cache"],"devDependencies":{"del":"^2.2.2","webpack":"^1.0.0","chalk":"^1.1.3","cli-highlight":"^1.1.4","diff":"^3.0.1","dir-compare":"^1.1.0","on-build-webpack":"^0.1.0"},"buildDependencies":{"babel":"^5.8.23"},"gitHead":"8becac5581cc96077337b6711ee447cf7270f200","_id":"offline-plugin@4.5.0-beta.3","_shasum":"1428ce916ae3e6713d759b4f5c30bcb43464b5be","_from":".","_npmVersion":"3.10.3","_nodeVersion":"6.7.0","_npmUser":{"name":"nekr","email":"nekr.fabula@gmail.com"},"dist":{"shasum":"1428ce916ae3e6713d759b4f5c30bcb43464b5be","tarball":"https://registry.npmjs.org/offline-plugin/-/offline-plugin-4.5.0-beta.3.tgz"},"maintainers":[{"name":"nekr","email":"nekr.fabula@gmail.com"}],"_npmOperationalInternal":{"host":"packages-12-west.internal.npmjs.com","tmp":"tmp/offline-plugin-4.5.0-beta.3.tgz_1479830540150_0.11686130031011999"},"directories":{}},"4.5.0-beta.4":{"name":"offline-plugin","version":"4.5.0-beta.4","description":"offline-plugin for webpack","main":"lib/index.js","files":["lib/","tpls/","runtime.js","empty-entry.js"],"scripts":{"test":"node tests/legacy/run","build":"babel src/ -d lib/","watch":"npm run build -- --watch","install:build-deps":"node build/install.js"},"repository":{"type":"git","url":"git+https://github.com/NekR/offline-plugin.git"},"author":{"name":"Arthur Stolyar","email":"nekr.fabula@gmail.com"},"license":"MIT","dependencies":{"deep-extend":"^0.4.0","ejs":"^2.3.4","loader-utils":"0.2.x","minimatch":"^3.0.3","slash":"^1.0.0"},"bugs":{"url":"https://github.com/NekR/offline-plugin/issues"},"homepage":"https://github.com/NekR/offline-plugin","keywords":["webpack","plugin","offline","cache","service-worker","serviceworker","appcache","application cache"],"devDependencies":{"del":"^2.2.2","webpack":"^1.0.0","chalk":"^1.1.3","cli-highlight":"^1.1.4","diff":"^3.0.1","dir-compare":"^1.1.0","on-build-webpack":"^0.1.0"},"buildDependencies":{"babel":"^5.8.23"},"gitHead":"467d97f7d9372d362476d830a3c71768670d43bb","_id":"offline-plugin@4.5.0-beta.4","_shasum":"2f4ad32edb2468c0fa5512d8b847ae70109f366b","_from":".","_npmVersion":"3.10.3","_nodeVersion":"6.7.0","_npmUser":{"name":"nekr","email":"nekr.fabula@gmail.com"},"dist":{"shasum":"2f4ad32edb2468c0fa5512d8b847ae70109f366b","tarball":"https://registry.npmjs.org/offline-plugin/-/offline-plugin-4.5.0-beta.4.tgz"},"maintainers":[{"name":"nekr","email":"nekr.fabula@gmail.com"}],"_npmOperationalInternal":{"host":"packages-18-east.internal.npmjs.com","tmp":"tmp/offline-plugin-4.5.0-beta.4.tgz_1479920380729_0.1942384298890829"},"directories":{}},"4.5.0-beta.5":{"name":"offline-plugin","version":"4.5.0-beta.5","description":"offline-plugin for webpack","main":"lib/index.js","files":["lib/","tpls/","runtime.js","empty-entry.js"],"scripts":{"test":"node tests/legacy/run","build":"babel src/ -d lib/","watch":"npm run build -- --watch","install:build-deps":"node build/install.js"},"repository":{"type":"git","url":"git+https://github.com/NekR/offline-plugin.git"},"author":{"name":"Arthur Stolyar","email":"nekr.fabula@gmail.com"},"license":"MIT","dependencies":{"deep-extend":"^0.4.0","ejs":"^2.3.4","loader-utils":"0.2.x","minimatch":"^3.0.3","slash":"^1.0.0"},"bugs":{"url":"https://github.com/NekR/offline-plugin/issues"},"homepage":"https://github.com/NekR/offline-plugin","keywords":["webpack","plugin","offline","cache","service-worker","serviceworker","appcache","application cache"],"devDependencies":{"del":"^2.2.2","webpack":"^1.0.0","chalk":"^1.1.3","cli-highlight":"^1.1.4","diff":"^3.0.1","dir-compare":"^1.1.0","on-build-webpack":"^0.1.0"},"buildDependencies":{"babel":"^5.8.23"},"gitHead":"84a94e475d694450f5e52df20067b609d81a4675","_id":"offline-plugin@4.5.0-beta.5","_shasum":"db100fbb4db8d327bf43a84bd7f2294868bd69c3","_from":".","_npmVersion":"3.10.3","_nodeVersion":"6.7.0","_npmUser":{"name":"nekr","email":"nekr.fabula@gmail.com"},"dist":{"shasum":"db100fbb4db8d327bf43a84bd7f2294868bd69c3","tarball":"https://registry.npmjs.org/offline-plugin/-/offline-plugin-4.5.0-beta.5.tgz"},"maintainers":[{"name":"nekr","email":"nekr.fabula@gmail.com"}],"_npmOperationalInternal":{"host":"packages-12-west.internal.npmjs.com","tmp":"tmp/offline-plugin-4.5.0-beta.5.tgz_1479921616675_0.7792994419578463"},"directories":{}},"4.5.0-beta.6":{"name":"offline-plugin","version":"4.5.0-beta.6","description":"offline-plugin for webpack","main":"lib/index.js","files":["lib/","tpls/","runtime.js","empty-entry.js"],"scripts":{"test":"node tests/legacy/run","build":"babel src/ -d lib/","watch":"npm run build -- --watch","install:build-deps":"node build/install.js"},"repository":{"type":"git","url":"git+https://github.com/NekR/offline-plugin.git"},"author":{"name":"Arthur Stolyar","email":"nekr.fabula@gmail.com"},"license":"MIT","dependencies":{"deep-extend":"^0.4.0","ejs":"^2.3.4","loader-utils":"0.2.x","minimatch":"^3.0.3","slash":"^1.0.0"},"bugs":{"url":"https://github.com/NekR/offline-plugin/issues"},"homepage":"https://github.com/NekR/offline-plugin","keywords":["webpack","plugin","offline","cache","service-worker","serviceworker","appcache","application cache"],"devDependencies":{"del":"^2.2.2","webpack":"^1.0.0","chalk":"^1.1.3","cli-highlight":"^1.1.4","diff":"^3.0.1","dir-compare":"^1.1.0","on-build-webpack":"^0.1.0"},"buildDependencies":{"babel":"^5.8.23"},"gitHead":"33a9b99fa6447f343a1d23bdada3031ce485c1bc","_id":"offline-plugin@4.5.0-beta.6","_shasum":"30298040b363757f3877ea0adbe901c4300b1df3","_from":".","_npmVersion":"3.10.3","_nodeVersion":"6.7.0","_npmUser":{"name":"nekr","email":"nekr.fabula@gmail.com"},"dist":{"shasum":"30298040b363757f3877ea0adbe901c4300b1df3","tarball":"https://registry.npmjs.org/offline-plugin/-/offline-plugin-4.5.0-beta.6.tgz"},"maintainers":[{"name":"nekr","email":"nekr.fabula@gmail.com"}],"_npmOperationalInternal":{"host":"packages-18-east.internal.npmjs.com","tmp":"tmp/offline-plugin-4.5.0-beta.6.tgz_1480128984210_0.11255481722764671"},"directories":{}},"4.5.0":{"name":"offline-plugin","version":"4.5.0","description":"offline-plugin for webpack","main":"lib/index.js","files":["lib/","tpls/","runtime.js","empty-entry.js"],"scripts":{"test":"node tests/legacy/run","build":"babel src/ -d lib/","watch":"npm run build -- --watch","install:build-deps":"node build/install.js"},"repository":{"type":"git","url":"git+https://github.com/NekR/offline-plugin.git"},"author":{"name":"Arthur Stolyar","email":"nekr.fabula@gmail.com"},"license":"MIT","dependencies":{"deep-extend":"^0.4.0","ejs":"^2.3.4","loader-utils":"0.2.x","minimatch":"^3.0.3","slash":"^1.0.0"},"bugs":{"url":"https://github.com/NekR/offline-plugin/issues"},"homepage":"https://github.com/NekR/offline-plugin","keywords":["webpack","plugin","offline","cache","service-worker","serviceworker","appcache","application cache"],"devDependencies":{"del":"^2.2.2","webpack":"^1.0.0","chalk":"^1.1.3","cli-highlight":"^1.1.4","diff":"^3.0.1","dir-compare":"^1.1.0","on-build-webpack":"^0.1.0"},"buildDependencies":{"babel":"^5.8.23"},"gitHead":"c2a49d469ab1e1f458742c99e704f81155f96857","_id":"offline-plugin@4.5.0","_shasum":"8e0c39bacae7ce5a32dfeef953db07cb304652f4","_from":".","_npmVersion":"3.10.3","_nodeVersion":"6.7.0","_npmUser":{"name":"nekr","email":"nekr.fabula@gmail.com"},"dist":{"shasum":"8e0c39bacae7ce5a32dfeef953db07cb304652f4","tarball":"https://registry.npmjs.org/offline-plugin/-/offline-plugin-4.5.0.tgz"},"maintainers":[{"name":"nekr","email":"nekr.fabula@gmail.com"}],"_npmOperationalInternal":{"host":"packages-18-east.internal.npmjs.com","tmp":"tmp/offline-plugin-4.5.0.tgz_1480381047966_0.820950475288555"},"directories":{}},"4.5.1":{"name":"offline-plugin","version":"4.5.1","description":"offline-plugin for webpack","main":"lib/index.js","files":["lib/","tpls/","runtime.js","empty-entry.js"],"scripts":{"test":"node tests/legacy/run","build":"babel src/ -d lib/","watch":"npm run build -- --watch","install:build-deps":"node build/install.js"},"repository":{"type":"git","url":"git+https://github.com/NekR/offline-plugin.git"},"author":{"name":"Arthur Stolyar","email":"nekr.fabula@gmail.com"},"license":"MIT","dependencies":{"deep-extend":"^0.4.0","ejs":"^2.3.4","loader-utils":"0.2.x","minimatch":"^3.0.3","slash":"^1.0.0"},"bugs":{"url":"https://github.com/NekR/offline-plugin/issues"},"homepage":"https://github.com/NekR/offline-plugin","keywords":["webpack","plugin","offline","cache","service-worker","serviceworker","appcache","application cache"],"devDependencies":{"del":"^2.2.2","webpack":"^1.0.0","chalk":"^1.1.3","cli-highlight":"^1.1.4","diff":"^3.0.1","dir-compare":"^1.1.0","on-build-webpack":"^0.1.0"},"buildDependencies":{"babel":"^5.8.23"},"gitHead":"c2a49d469ab1e1f458742c99e704f81155f96857","_id":"offline-plugin@4.5.1","_shasum":"bcb33b267d409727756ec9f55cadd17f0f408a83","_from":".","_npmVersion":"3.10.3","_nodeVersion":"6.7.0","_npmUser":{"name":"nekr","email":"nekr.fabula@gmail.com"},"dist":{"shasum":"bcb33b267d409727756ec9f55cadd17f0f408a83","tarball":"https://registry.npmjs.org/offline-plugin/-/offline-plugin-4.5.1.tgz"},"maintainers":[{"name":"nekr","email":"nekr.fabula@gmail.com"}],"_npmOperationalInternal":{"host":"packages-18-east.internal.npmjs.com","tmp":"tmp/offline-plugin-4.5.1.tgz_1480381166449_0.6695257164537907"},"directories":{}},"4.5.2":{"name":"offline-plugin","version":"4.5.2","description":"offline-plugin for webpack","main":"lib/index.js","files":["lib/","tpls/","runtime.js","empty-entry.js"],"scripts":{"test":"node tests/legacy/run","build":"babel src/ -d lib/","watch":"npm run build -- --watch","install:build-deps":"node build/install.js"},"repository":{"type":"git","url":"git+https://github.com/NekR/offline-plugin.git"},"author":{"name":"Arthur Stolyar","email":"nekr.fabula@gmail.com"},"license":"MIT","dependencies":{"deep-extend":"^0.4.0","ejs":"^2.3.4","loader-utils":"0.2.x","minimatch":"^3.0.3","slash":"^1.0.0"},"bugs":{"url":"https://github.com/NekR/offline-plugin/issues"},"homepage":"https://github.com/NekR/offline-plugin","keywords":["webpack","plugin","offline","cache","service-worker","serviceworker","appcache","application cache"],"devDependencies":{"del":"^2.2.2","webpack":"^1.0.0","chalk":"^1.1.3","cli-highlight":"^1.1.4","diff":"^3.0.1","dir-compare":"^1.1.0","on-build-webpack":"^0.1.0"},"buildDependencies":{"babel":"^5.8.23"},"gitHead":"4195b276f3c9aa904910f8742fea1b4a3e90879f","_id":"offline-plugin@4.5.2","_shasum":"c0d1bc5c3545bbb5711b412c46355948bebeffca","_from":".","_npmVersion":"3.10.3","_nodeVersion":"6.7.0","_npmUser":{"name":"nekr","email":"nekr.fabula@gmail.com"},"dist":{"shasum":"c0d1bc5c3545bbb5711b412c46355948bebeffca","tarball":"https://registry.npmjs.org/offline-plugin/-/offline-plugin-4.5.2.tgz"},"maintainers":[{"name":"nekr","email":"nekr.fabula@gmail.com"}],"_npmOperationalInternal":{"host":"packages-18-east.internal.npmjs.com","tmp":"tmp/offline-plugin-4.5.2.tgz_1480381338829_0.16611027414910495"},"directories":{}},"4.5.3":{"name":"offline-plugin","version":"4.5.3","description":"offline-plugin for webpack","main":"lib/index.js","files":["lib/","tpls/","runtime.js","empty-entry.js"],"scripts":{"test":"node tests/legacy/run","build":"babel src/ -d lib/","watch":"npm run build -- --watch","install:build-deps":"node build/install.js"},"repository":{"type":"git","url":"git+https://github.com/NekR/offline-plugin.git"},"author":{"name":"Arthur Stolyar","email":"nekr.fabula@gmail.com"},"license":"MIT","dependencies":{"deep-extend":"^0.4.0","ejs":"^2.3.4","loader-utils":"0.2.x","minimatch":"^3.0.3","slash":"^1.0.0"},"bugs":{"url":"https://github.com/NekR/offline-plugin/issues"},"homepage":"https://github.com/NekR/offline-plugin","keywords":["webpack","plugin","offline","cache","caching","storage","service-worker","serviceworker","appcache","application cache","pwa","progressive web apps","app-shell","appshell"],"devDependencies":{"del":"^2.2.2","webpack":"^1.0.0","chalk":"^1.1.3","cli-highlight":"^1.1.4","diff":"^3.0.1","dir-compare":"^1.1.0","on-build-webpack":"^0.1.0"},"buildDependencies":{"babel":"^5.8.23"},"gitHead":"1a95e830101b16c1d2522aed5ca315cfb40e97bf","_id":"offline-plugin@4.5.3","_shasum":"39c2bd7a3fc74fadaa601d0aa20dc4f74ae24add","_from":".","_npmVersion":"3.10.3","_nodeVersion":"6.7.0","_npmUser":{"name":"nekr","email":"nekr.fabula@gmail.com"},"dist":{"shasum":"39c2bd7a3fc74fadaa601d0aa20dc4f74ae24add","tarball":"https://registry.npmjs.org/offline-plugin/-/offline-plugin-4.5.3.tgz"},"maintainers":[{"name":"nekr","email":"nekr.fabula@gmail.com"}],"_npmOperationalInternal":{"host":"packages-18-east.internal.npmjs.com","tmp":"tmp/offline-plugin-4.5.3.tgz_1480947638317_0.8199522418435663"},"directories":{}},"4.5.4":{"name":"offline-plugin","version":"4.5.4","description":"offline-plugin for webpack","main":"lib/index.js","files":["lib/","tpls/","runtime.js","empty-entry.js"],"scripts":{"test":"node tests/legacy/run","build":"babel src/ -d lib/","watch":"npm run build -- --watch","install:build-deps":"node build/install.js"},"repository":{"type":"git","url":"git+https://github.com/NekR/offline-plugin.git"},"author":{"name":"Arthur Stolyar","email":"nekr.fabula@gmail.com"},"license":"MIT","dependencies":{"deep-extend":"^0.4.0","ejs":"^2.3.4","loader-utils":"0.2.x","minimatch":"^3.0.3","slash":"^1.0.0"},"bugs":{"url":"https://github.com/NekR/offline-plugin/issues"},"homepage":"https://github.com/NekR/offline-plugin","keywords":["webpack","plugin","offline","cache","caching","storage","service-worker","serviceworker","appcache","application cache","pwa","progressive web apps","app-shell","appshell"],"devDependencies":{"del":"^2.2.2","webpack":"^1.0.0","chalk":"^1.1.3","cli-highlight":"^1.1.4","diff":"^3.0.1","dir-compare":"^1.1.0","on-build-webpack":"^0.1.0"},"buildDependencies":{"babel":"^5.8.23"},"gitHead":"b23820b904f5715e7d5bb3ae0ce14da06972ec9e","_id":"offline-plugin@4.5.4","_shasum":"820f5e2465c160c8b2fad2835747df9c3b4dc0cc","_from":".","_npmVersion":"3.10.3","_nodeVersion":"6.7.0","_npmUser":{"name":"nekr","email":"nekr.fabula@gmail.com"},"dist":{"shasum":"820f5e2465c160c8b2fad2835747df9c3b4dc0cc","tarball":"https://registry.npmjs.org/offline-plugin/-/offline-plugin-4.5.4.tgz"},"maintainers":[{"name":"nekr","email":"nekr.fabula@gmail.com"}],"_npmOperationalInternal":{"host":"packages-18-east.internal.npmjs.com","tmp":"tmp/offline-plugin-4.5.4.tgz_1483886796628_0.9688704053405672"},"directories":{}},"4.5.5":{"name":"offline-plugin","version":"4.5.5","description":"offline-plugin for webpack","main":"lib/index.js","files":["lib/","tpls/","runtime.js","empty-entry.js"],"scripts":{"test":"node tests/legacy/run","build":"babel src/ -d lib/","watch":"npm run build -- --watch","install:build-deps":"node build/install.js"},"repository":{"type":"git","url":"git+https://github.com/NekR/offline-plugin.git"},"author":{"name":"Arthur Stolyar","email":"nekr.fabula@gmail.com"},"license":"MIT","dependencies":{"deep-extend":"^0.4.0","ejs":"^2.3.4","loader-utils":"0.2.x","minimatch":"^3.0.3","slash":"^1.0.0"},"bugs":{"url":"https://github.com/NekR/offline-plugin/issues"},"homepage":"https://github.com/NekR/offline-plugin","keywords":["webpack","plugin","offline","cache","caching","storage","service-worker","serviceworker","appcache","application cache","pwa","progressive web apps","app-shell","appshell"],"devDependencies":{"del":"^2.2.2","webpack":"^1.0.0","chalk":"^1.1.3","cli-highlight":"^1.1.4","diff":"^3.0.1","dir-compare":"^1.1.0","on-build-webpack":"^0.1.0"},"buildDependencies":{"babel":"^5.8.23"},"gitHead":"bce7564a88f037aef048ed7455760c2eb2083a18","_id":"offline-plugin@4.5.5","_shasum":"484b7db32497f1813a0b3e7c931a4cc8fc9563ec","_from":".","_npmVersion":"3.10.3","_nodeVersion":"6.7.0","_npmUser":{"name":"nekr","email":"nekr.fabula@gmail.com"},"dist":{"shasum":"484b7db32497f1813a0b3e7c931a4cc8fc9563ec","tarball":"https://registry.npmjs.org/offline-plugin/-/offline-plugin-4.5.5.tgz"},"maintainers":[{"name":"nekr","email":"nekr.fabula@gmail.com"}],"_npmOperationalInternal":{"host":"packages-12-west.internal.npmjs.com","tmp":"tmp/offline-plugin-4.5.5.tgz_1484362070729_0.8467640113085508"},"directories":{}}},"readme":"# `offline-plugin` for webpack\n\n[![npm](https://img.shields.io/npm/v/offline-plugin.svg?maxAge=3600&v4)](https://www.npmjs.com/package/offline-plugin)\n[![npm](https://img.shields.io/npm/dm/offline-plugin.svg?maxAge=3600)](https://www.npmjs.com/package/offline-plugin)\n[![Join the chat at https://gitter.im/NekR/offline-plugin](https://badges.gitter.im/NekR/offline-plugin.svg)](https://gitter.im/NekR/offline-plugin?utm_source=badge&utm_medium=badge&utm_campaign=pr-badge&utm_content=badge)\n\nThis plugin is intended to provide an offline experience for **webpack** projects. It uses **ServiceWorker**, and **AppCache** as a fallback under the hood. Simply include this plugin in your ``webpack.config``, and the accompanying runtime in your client script, and your project will become offline ready by caching all (or some) of the webpack output assets.\n\n## Install\n\n`npm install offline-plugin [--save-dev]`\n\n## Setup\n\nFirst, instantiate the plugin with [options](#options) in your `webpack.config`:\n\n```js\n// webpack.config.js example\n\nvar OfflinePlugin = require('offline-plugin');\n\nmodule.exports = {\n  // ...\n\n  plugins: [\n    // ... other plugins\n    // it always better if OfflinePlugin is the last plugin added\n    new OfflinePlugin()\n  ]\n  // ...\n}\n\n```\n\nThen, add the [runtime](docs/runtime.md) into your entry file (typically main entry):\n\n```js\nrequire('offline-plugin/runtime').install();\n```\n\n## Docs\n\n* [Caches](docs/caches.md)\n* [Update process](docs/updates.md)\n* [FAQ](FAQ.md)\n\n## Options\n\n**All options are optional and `offline-plugin` can be used without specifying them.** Also see full list of default options [here](https://github.com/NekR/offline-plugin/blob/master/src/index.js#L9).\n\n#### `caches: 'all' | Object`\n\nAllows you to define what to cache and how.\n\n* `'all'`: means that everything (all the webpack output assets) and URLs listed in `externals` option will be cached on install.\n* `Object`: Object with 3 possible `Array<string>` sections (properties): `main`, `additional`, `optional`. All sections are optional and by default are empty (no assets added).\n\n[More details about `caches`](docs/caches.md)\n\n> Default: `'all'`.\n\n#### `publicPath: string`\n\nSame as `webpack`'s `output.publicPath` option. Useful to specify or override `publicPath` specifically for `offline-plugin`. When not specified, `webpack`'s `output.publicPath` value is used. When `webpack`'s `output.publicPath` value isn't specified, relative paths are used (see `relativePaths` option).\n\n> __Examples:__  \n`publicPath: '/project/'`  \n`publicPath: 'https://example.com/project'`  \n\n#### `responseStrategy: 'cache-first' |'network-first'`\nResponse strategy. Whether to use a cache or network first for responses.\n> Default: `'cache-first'`.\n\n#### `updateStrategy: 'changed' | 'all'`\nCache update strategy. [More details about `updateStrategy`](docs/update-strategies.md)  \n> Default: `'changed'`.\n\n#### `externals: Array<string>`\nAllows you to specify _external_ assets (assets which aren't generated by webpack) that should be included in the cache. If you don't change the `caches` configuration option then it should be enough to simply add assets to this (`externals`) option. For other details and more advanced use cases see [`caches` docs](docs/caches.md).\n\n> Default: `null`  \n> **Example value:** `['fonts/roboto.woff']`\n\n#### `excludes: Array<string | globs_pattern>`\nExcludes matched assets from being added to the [caches](https://github.com/NekR/offline-plugin#caches-all--object). Exclusion is performed before _rewrite_ happens.  \n[Learn more about assets _rewrite_](docs/rewrite.md)\n\n> Default: `['**/.*', '**/*.map']`  \n> _Excludes all files which start with `.` or end with `.map`_\n\n#### `relativePaths: boolean`\nWhen set to `true`, all the asset paths generated in the cache will be relative to the `ServiceWorker` file or the `AppCache` folder location respectively.  \n`publicPath` option is ignored when this is **explicitly** set to `true`.\n> **Default:** `true`\n\n#### `version: string | (plugin: OfflinePlugin) => void`\nVersion of the cache. Can be a function, which is useful in _watch-mode_ when you need to apply dynamic value.\n\n* `Function` is called with the plugin instance as the first argument\n* `string` which can be interpolated with `[hash]` token\n\n> Default: _Current date_\n\n#### `rewrites: Function | Object`\n\nRewrite function or rewrite map (`Object`). Useful when assets are served in a different way from the client perspective, e.g. usually `index.html` is served as `/`.\n\n[See more about `rewrites` option and default function](docs/rewrite.md)\n\n#### `cacheMaps: Array<Object>`\n\nSee [documentation of `cacheMaps`](docs/cache-maps.md) for syntax and usage examples\n\n\n#### `ServiceWorker: Object | null | false`\n\nSettings for the `ServiceWorker` cache. Use `null` or `false` to disable `ServiceWorker` generation.\n\n* `output`: `string`. Relative (from the _webpack_'s config `output.path`) output path for emitted script.  \n_Default:_ `'sw.js'`\n\n* `entry`: `string`. Relative or absolute path to the file which will be used as the `ServiceWorker` entry/bootstrapping. Useful to implement additional features or handlers for Service Worker events such as `push`, `sync`, etc.  \n_Default:_ _empty file_\n\n* `scope`: `string`. Reflects [ServiceWorker.register](https://developer.mozilla.org/en-US/docs/Web/API/ServiceWorkerContainer/register)'s `scope` option.  \n_Default:_ `null`\n\n* `cacheName`: `string`. **This option is very dangerous. Touching it you must realize that you should **not** change it after you go production. Changing it may corrupt the cache and leave old caches on users' devices. This option is useful when you need to run more than one project on _the same domain_.  \n_Default:_ _`''`_ (empty string)\n_Example:_ `'my-project'`\n\n* `navigateFallbackURL`: `string`. The URL that should be returned from the cache when a requested navigation URL isn't available on the cache or network. Similar to the `AppCache.FALLBACK` option.  \n_Example:_ `navigateFallbackURL: '/'`\n\n* `events`: `boolean`. Enables runtime events for the ServiceWorker. For supported events see `Runtime`'s `install()` options.\n_Default:_ `false`\n\n* `publicPath`: `string`. Provides a way to override `ServiceWorker`'s script file location on the server. Should be an exact path to the generated `ServiceWorker` file.\n_Default:_ `null`\n_Example:_ `'my/new/path/sw.js'`\n\n* `prefetchRequest`: `Object`. Provides a way to specify [request init options](https://developer.mozilla.org/en-US/docs/Web/API/Request/Request) for pre-fetch requests (pre-cache requests on `install` event). Allowed options: `credentials`, `headers`, `mode`, `cache`.  \n_Default:_ `{ credentials: 'omit', mode: 'cors' }`  \n_Example:_ `{ credentials: 'same-origin' }`  \n\n#### `AppCache: Object | null | false`\n\nSettings for the `AppCache` cache. Use `null` or `false` to disable `AppCache` generation.\n\n > _**Warning**_: Officially the AppCache feature [has been deprecated](https://developer.mozilla.org/en-US/docs/Web/HTML/Using_the_application_cache) in favour of Service Workers.  However, Service Workers are still being implemented across all browsers (you can track progress [here](https://jakearchibald.github.io/isserviceworkerready/)) so AppCache is unlikely to suddenly disappear.  Therefore please don't be afraid to use the AppCache feature if you have a need to provide offline support to browsers that do not support Service Workers, but it is good to be aware of this fact and make a deliberate decision on your configuration.\n\n* `directory`: `string`. Relative (from the _webpack_'s config `output.path`) output directly path for the `AppCache` emitted files.  \n_Default:_ `'appcache/'`\n\n* `NETWORK`: `string`. Reflects `AppCache`'s `NETWORK` section.  \n_Default:_ `'*'`\n\n* `FALLBACK`: `Object`. Reflects `AppCache`'s `FALLBACK` section. Useful for single page applications making use of HTML5 routing or for displaying custom _Offline page_.  \n_Example 1:_ `{ '/blog': '/' }` will map all requests starting with `/blog` to the domain roboto when request fails.  \n_Example 2:_ `{ '/': '/offline-page.html' }` will return contents of `/offline-page.html` for any failed request.  \n_Default:_ `null`\n\n* `events`: `boolean`. Enables runtime events for AppCache. For supported events see `Runtime`'s `install()` options.  \n_Default:_ `false`\n\n* `publicPath`: `string`. Provides a way to override `AppCache`'s folder location on the server. Should be exact path to the generated `AppCache` folder.  \n_Default:_ `null`  \n_Example:_ `'my/new/path/appcache'`\n\n* `disableInstall` :`boolean`. Disable the automatic installation of the `AppCache` when calling to `runtime.install()`. Useful when you to specify `<html manifest=\"...\">` attribute manually (to cache every page user visits).  \n_Default:_ `false`\n\n* `includeCrossOrigin` :`boolean`. Outputs cross-origin URLs into `AppCache`'s manifest file. **Cross-origin URLs aren't supported in `AppCache` when used on HTTPS.**  \n_Default:_ `false`\n\n## Who is using `offline-plugin`\n\n### Projects\n\n* [React Boilerplate](https://github.com/mxstbr/react-boilerplate)\n* [Phenomic](https://phenomic.io)\n* [Gatsby](https://github.com/gatsbyjs/gatsby)\n* [Angular CLI](https://github.com/angular/angular-cli)\n* [React, Universally](https://github.com/ctrlplusb/react-universally)\n\n### PWAs\n\n* [Offline Kanban](https://offline-kanban.herokuapp.com) ([source](https://github.com/sarmadsangi/offline-kanban))\n* [Preact](https://preactjs.com/) ([source](https://github.com/developit/preact-www))\n* [Omroep West (_Proof of Concept_)](https://omroep-west.now.sh/)\n\n\n_If you are using `offline-plugin`, feel free to submit a PR to add your project to this list._\n\n## Like `offline-plugin`?\n\nSupport it by giving [feedback](https://github.com/NekR/offline-plugin/issues), contributing or just by  starring the project!\n\n\n## License\n\n[MIT](LICENSE.md)\n\n\n## CHANGELOG\n\n[CHANGELOG](CHANGELOG.md)\n","maintainers":[{"name":"nekr","email":"nekr.fabula@gmail.com"}],"time":{"modified":"2017-01-14T02:47:52.975Z","created":"2015-09-11T17:06:44.517Z","0.0.1":"2015-09-11T17:06:44.517Z","0.0.2":"2015-09-18T20:45:24.360Z","1.0.0":"2015-09-20T11:29:53.387Z","1.0.1":"2015-09-20T12:01:18.758Z","1.0.2":"2015-09-20T15:02:19.049Z","1.0.3":"2015-09-20T21:46:16.074Z","1.1.0":"2015-09-23T10:41:30.858Z","1.2.0":"2015-09-24T22:29:55.157Z","1.2.1":"2015-09-26T19:36:08.141Z","1.3.0":"2015-10-12T23:04:17.321Z","1.3.1":"2015-10-22T08:04:58.622Z","2.0.0":"2016-01-21T15:01:53.405Z","2.0.1":"2016-01-21T16:21:51.674Z","2.0.2":"2016-01-21T16:28:11.061Z","2.0.3":"2016-02-03T09:29:46.526Z","2.0.4":"2016-02-09T00:46:58.520Z","2.1.0":"2016-04-02T18:55:26.187Z","3.0.0":"2016-04-07T18:47:41.993Z","3.0.1":"2016-04-08T07:43:30.993Z","2.1.1":"2016-04-22T09:48:27.841Z","3.1.0":"2016-04-25T18:29:53.364Z","3.1.1":"2016-04-26T23:25:20.445Z","2.2.0":"2016-04-26T23:28:00.499Z","2.2.1":"2016-05-07T11:58:03.242Z","3.2.0":"2016-05-08T00:31:46.802Z","3.2.1":"2016-05-09T08:57:49.104Z","3.3.0":"2016-06-04T07:28:35.891Z","3.3.1":"2016-06-09T06:04:55.627Z","3.4.0":"2016-06-17T06:28:46.294Z","3.4.1":"2016-06-30T12:54:46.143Z","3.4.2":"2016-07-11T13:27:23.666Z","4.0.0":"2016-07-19T13:32:04.925Z","4.1.0":"2016-08-31T22:39:51.386Z","4.2.0":"2016-10-03T09:30:43.268Z","4.2.1":"2016-10-04T11:44:27.385Z","4.3.0":"2016-10-15T15:25:24.428Z","4.3.1":"2016-10-15T18:45:11.255Z","4.4.0":"2016-10-22T13:01:40.995Z","4.4.1":"2016-10-26T16:30:23.006Z","4.5.0-beta":"2016-11-21T22:12:23.323Z","4.5.0-beta.1":"2016-11-22T12:50:53.606Z","4.5.0-beta.2":"2016-11-22T13:32:06.168Z","4.5.0-beta.3":"2016-11-22T16:02:22.323Z","4.5.0-beta.4":"2016-11-23T16:59:41.385Z","4.5.0-beta.5":"2016-11-23T17:20:19.025Z","4.5.0-beta.6":"2016-11-26T02:56:24.898Z","4.5.0":"2016-11-29T00:57:28.595Z","4.5.1":"2016-11-29T00:59:27.099Z","4.5.2":"2016-11-29T01:02:19.469Z","4.5.3":"2016-12-05T14:20:39.037Z","4.5.4":"2017-01-08T14:46:37.339Z","4.5.5":"2017-01-14T02:47:52.975Z"},"homepage":"https://github.com/NekR/offline-plugin","repository":{"type":"git","url":"git+https://github.com/NekR/offline-plugin.git"},"author":{"name":"Arthur Stolyar","email":"nekr.fabula@gmail.com"},"bugs":{"url":"https://github.com/NekR/offline-plugin/issues"},"license":"MIT","readmeFilename":"README.md","keywords":["webpack","plugin","offline","cache","caching","storage","service-worker","serviceworker","appcache","application cache","pwa","progressive web apps","app-shell","appshell"],"users":{"moimikey":true,"fadihania":true,"langri-sha":true,"jacobmischka":true,"halfzebra":true,"razr9":true},"_attachments":{},"_etag":"W/\"58799158-16354\"","_lastModified":"Sat, 14 Jan 2017 02:47:52 GMT"}